[{"theme":"","_id":"65e8abcba5e6cd0e9b7b31c3","uid":"07ZwS","fen":"1nkr3r/1ppn1pp1/p2p3p/3N4/P3PP1b/3BB1PP/1PP5/2KR3R b - - 0 18","moves":"h4g3 d5e7","rating":1023,"ratingDeviation":83,"randomNumberQuery":61,"popularity":83,"nbPlays":84,"themes":["mate","mateIn1","middlegame","oneMove","smotheredMate"],"gameUrl":"https://lichess.org/ELkBZP0D/black#35","openingFamily":"Vienna_Game","openingVariation":"Vienna_Game_Other_variations","__v":0},{"theme":"","_id":"65e8abd7a5e6cd0e9b7b5890","uid":"0Cbzh","fen":"r2qkbnr/pp2pppp/8/2p1n3/3p4/2P2P2/PP1PNP1P/R1BQKB1R w KQkq - 0 8","moves":"c3d4 e5f3","rating":1038,"ratingDeviation":211,"randomNumberQuery":4086,"popularity":38,"nbPlays":22,"themes":["mate","mateIn1","oneMove","opening","smotheredMate"],"gameUrl":"https://lichess.org/cCVSiFr7#14","openingFamily":"","openingVariation":"","__v":0},{"theme":"","_id":"65e8ac3aa5e6cd0e9b7cb50a","uid":"0wc7l","fen":"2b3rk/p5rn/1np5/qp2Q3/4PNpP/2N2P2/PPP5/1K3B1R b - - 2 23","moves":"b6d7 f4g6","rating":1037,"ratingDeviation":84,"randomNumberQuery":4228,"popularity":88,"nbPlays":294,"themes":["master","mate","mateIn1","middlegame","oneMove","pin","smotheredMate"],"gameUrl":"https://lichess.org/WjplygF8/black#45","openingFamily":"","openingVariation":"","__v":0},{"theme":"","_id":"65e8ac8ea5e6cd0e9b7dde4b","uid":"1ZK1x","fen":"6k1/5ppp/4pn2/1p1qN2Q/p1pr4/6PK/1P3P1P/8 b - - 5 32","moves":"d4e4 h5f7 g8h8 f7f8 f6g8 e5f7","rating":1034,"ratingDeviation":75,"randomNumberQuery":2599,"popularity":95,"nbPlays":5509,"themes":["endgame","long","mate","mateIn3","smotheredMate"],"gameUrl":"https://lichess.org/9lr1UjTE/black#63","openingFamily":"","openingVariation":"","__v":0},{"theme":"","_id":"65e8ad06a5e6cd0e9b7f81e9","uid":"2Ru0J","fen":"r1b2rk1/2p2pp1/3p1n1p/2b1pP2/pp1nP2P/2NP2P1/PPPB1NQ1/2KR3R w - - 0 16","moves":"c3b1 d4e2","rating":1037,"ratingDeviation":99,"randomNumberQuery":8532,"popularity":58,"nbPlays":79,"themes":["mate","mateIn1","middlegame","oneMove","smotheredMate"],"gameUrl":"https://lichess.org/a7JArLg4#30","openingFamily":"Kings_Gambit_Declined","openingVariation":"Kings_Gambit_Declined_Keenes_Defense","__v":0},{"theme":"","_id":"65e8ad1fa5e6cd0e9b7fdd65","uid":"2dtwA","fen":"3r1rk1/4bppp/4p3/1N2B3/1nQ2P2/6Pn/1P4BP/4NRqK w - - 11 26","moves":"f1g1 h3f2","rating":1024,"ratingDeviation":98,"randomNumberQuery":442,"popularity":79,"nbPlays":244,"themes":["mate","mateIn1","middlegame","oneMove","smotheredMate"],"gameUrl":"https://lichess.org/P7Dnuyd7#50","openingFamily":"","openingVariation":"","__v":0},{"theme":"","_id":"65e8ad71a5e6cd0e9b80e4e1","uid":"3CLTR","fen":"r1b1k2r/1p2bpp1/p2pp3/7p/1PP1PPn1/N1NQ4/P2Bn1PP/R4RqK w kq - 2 17","moves":"f1g1 g4f2","rating":1033,"ratingDeviation":82,"randomNumberQuery":6118,"popularity":94,"nbPlays":813,"themes":["mate","mateIn1","middlegame","oneMove","smotheredMate"],"gameUrl":"https://lichess.org/3t5vnn6Y#32","openingFamily":"Sicilian_Defense","openingVariation":"Sicilian_Defense_Taimanov_Variation","__v":0},{"theme":"","_id":"65e8ad80a5e6cd0e9b8116c1","uid":"3IoU0","fen":"r1b2rk1/pp2b1pp/2B5/3pp2Q/8/1NP4n/PP4PP/RNB1R1qK w - - 3 16","moves":"e1g1 h3f2","rating":1032,"ratingDeviation":99,"randomNumberQuery":3076,"popularity":89,"nbPlays":159,"themes":["mate","mateIn1","oneMove","opening","smotheredMate"],"gameUrl":"https://lichess.org/tVHGcWYa#30","openingFamily":"French_Defense","openingVariation":"French_Defense_Advance_Variation","__v":0},{"theme":"","_id":"65e8adb2a5e6cd0e9b81c25d","uid":"3f7Mk","fen":"2rqkb1r/1b1pnpp1/p1n1p2p/1p1N4/4P2B/1B3N2/PP3PPP/R2QR1K1 b k - 3 12","moves":"g7g5 d5f6","rating":1020,"ratingDeviation":87,"randomNumberQuery":9200,"popularity":93,"nbPlays":579,"themes":["mate","mateIn1","middlegame","oneMove","smotheredMate"],"gameUrl":"https://lichess.org/OBK8M8c4/black#23","openingFamily":"Sicilian_Defense","openingVariation":"Sicilian_Defense_Smith-Morra_Gambit_Accepted","__v":0},{"theme":"","_id":"65e8adeda5e6cd0e9b829553","uid":"46WBh","fen":"r5Qk/b5pp/b1p4N/p7/4n3/8/Pq3PPP/R3R1K1 b - - 5 26","moves":"a8g8 h6f7","rating":1023,"ratingDeviation":76,"randomNumberQuery":7003,"popularity":100,"nbPlays":459,"themes":["mate","mateIn1","middlegame","oneMove","smotheredMate"],"gameUrl":"https://lichess.org/aKVsXxC8/black#51","openingFamily":"","openingVariation":"","__v":0},{"theme":"","_id":"65e8ae2da5e6cd0e9b837a5f","uid":"4afei","fen":"r3k2r/1p3ppp/3pbq2/2b3Q1/3n4/P4NP1/3BPP1P/3RKB1R w Kkq - 3 16","moves":"g5f6 d4c2","rating":1023,"ratingDeviation":76,"randomNumberQuery":9252,"popularity":92,"nbPlays":657,"themes":["mate","mateIn1","middlegame","oneMove","smotheredMate"],"gameUrl":"https://lichess.org/vj0CIL5S#30","openingFamily":"Benoni_Defense","openingVariation":"Benoni_Defense_Benoni_Gambit_Accepted","__v":0},{"theme":"","_id":"65e8ae3ca5e6cd0e9b83afcd","uid":"4haKF","fen":"B1b2rk1/5ppp/p7/1pb1p1B1/1n6/2NPP1P1/1PPQ3P/q1KR3R w - - 2 19","moves":"c3b1 b4a2","rating":1021,"ratingDeviation":93,"randomNumberQuery":6512,"popularity":65,"nbPlays":80,"themes":["mate","mateIn1","middlegame","oneMove","smotheredMate"],"gameUrl":"https://lichess.org/GnGChCaB#36","openingFamily":"","openingVariation":"","__v":0},{"theme":"","_id":"65e8ae88a5e6cd0e9b84c2bb","uid":"5HfUr","fen":"2r3k1/pb4bp/1p1p2p1/5p2/2P5/1P5n/P1Q1B1PP/BR3RqK w - - 8 29","moves":"f1g1 h3f2","rating":1028,"ratingDeviation":97,"randomNumberQuery":3836,"popularity":76,"nbPlays":271,"themes":["mate","mateIn1","middlegame","oneMove","smotheredMate"],"gameUrl":"https://lichess.org/pdfLmqo1#56","openingFamily":"","openingVariation":"","__v":0},{"theme":"","_id":"65e8aea1a5e6cd0e9b851a47","uid":"5T3MW","fen":"r3r1k1/5pb1/3p4/4p2Q/1P6/2P3Pn/P5BP/R4RqK w - - 5 41","moves":"f1g1 h3f2","rating":1025,"ratingDeviation":96,"randomNumberQuery":8540,"popularity":68,"nbPlays":211,"themes":["mate","mateIn1","middlegame","oneMove","smotheredMate"],"gameUrl":"https://lichess.org/uf4UPvYf#80","openingFamily":"","openingVariation":"","__v":0},{"theme":"","_id":"65e8aedda5e6cd0e9b85f0a9","uid":"5uw19","fen":"2kr1r2/1ppbq3/2n1pp2/1NPp1npp/3P4/P2QPN1P/4BPP1/R3K2R b KQ - 0 16","moves":"c6b8 b5a7","rating":1035,"ratingDeviation":85,"randomNumberQuery":4698,"popularity":89,"nbPlays":154,"themes":["mate","mateIn1","middlegame","oneMove","smotheredMate"],"gameUrl":"https://lichess.org/FDckI6XX/black#31","openingFamily":"Queens_Pawn_Game","openingVariation":"Queens_Pawn_Game_Other_variations","__v":0},{"theme":"","_id":"65e8aee7a5e6cd0e9b8614a9","uid":"5zU4p","fen":"r2qkbnr/pb1n1pp1/1p2p2p/2p5/4NB2/3P1NP1/PPP2PBP/R2Q1RK1 b kq - 5 9","moves":"g8e7 e4d6","rating":1028,"ratingDeviation":89,"randomNumberQuery":1413,"popularity":87,"nbPlays":395,"themes":["mate","mateIn1","oneMove","opening","smotheredMate"],"gameUrl":"https://lichess.org/1vrAttj3/black#17","openingFamily":"","openingVariation":"","__v":0},{"theme":"","_id":"65e8af1ba5e6cd0e9b86ca0f","uid":"6NJ9j","fen":"r2qkb1r/pp1bnppp/3p4/1N1Pp3/Q1P5/8/PP3PPP/R1B1KB1R b KQkq - 2 10","moves":"a7a6 b5d6","rating":1030,"ratingDeviation":79,"randomNumberQuery":1376,"popularity":94,"nbPlays":728,"themes":["mate","mateIn1","oneMove","opening","smotheredMate"],"gameUrl":"https://lichess.org/VaIX2SVV/black#19","openingFamily":"Sicilian_Defense","openingVariation":"Sicilian_Defense_Lasker-Pelikan_Variation","__v":0},{"theme":"","_id":"65e8af2da5e6cd0e9b8707ad","uid":"6VSgQ","fen":"r1bqkb1r/pp1ppppp/8/1Np5/4n3/5N2/PPPP1PPP/R1BQR1K1 b kq - 1 7","moves":"e4f6 b5d6","rating":1024,"ratingDeviation":85,"randomNumberQuery":3357,"popularity":89,"nbPlays":962,"themes":["mate","mateIn1","oneMove","opening","pin","smotheredMate"],"gameUrl":"https://lichess.org/G6oiufK6/black#13","openingFamily":"","openingVariation":"","__v":0},{"theme":"","_id":"65e8af58a5e6cd0e9b879d57","uid":"6ooSL","fen":"r4Qkr/3n1ppq/pp4N1/2p4p/8/2p4P/PPP1R3/2K2R2 b - - 3 30","moves":"d7f8 g6e7","rating":1037,"ratingDeviation":87,"randomNumberQuery":8623,"popularity":78,"nbPlays":671,"themes":["mate","mateIn1","middlegame","oneMove","smotheredMate"],"gameUrl":"https://lichess.org/ERdmZjS5/black#59","openingFamily":"","openingVariation":"","__v":0},{"theme":"","_id":"65e8af92a5e6cd0e9b886e6d","uid":"7G7sR","fen":"5k2/6pp/4Q3/5p2/Pp3P2/1P5n/6PP/5RqK w - - 5 38","moves":"f1g1 h3f2","rating":1021,"ratingDeviation":95,"randomNumberQuery":601,"popularity":73,"nbPlays":151,"themes":["endgame","master","masterVsMaster","mate","mateIn1","oneMove","smotheredMate"],"gameUrl":"https://lichess.org/qWPysZW4#74","openingFamily":"","openingVariation":"","__v":0},{"theme":"","_id":"65e8afc0a5e6cd0e9b89107f","uid":"7bdr2","fen":"r5k1/1Q2pr1p/p2p2p1/8/4PP2/7n/P5PP/R3R1qK w - - 5 27","moves":"e1g1 h3f2","rating":1032,"ratingDeviation":89,"randomNumberQuery":7661,"popularity":76,"nbPlays":364,"themes":["endgame","mate","mateIn1","oneMove","smotheredMate"],"gameUrl":"https://lichess.org/LKBzdGct#52","openingFamily":"","openingVariation":"","__v":0},{"theme":"","_id":"65e8afdfa5e6cd0e9b897e7d","uid":"7q7Mz","fen":"r5rk/1p4pp/p2b4/2pPp1N1/b3P1Q1/7P/6PK/2q2R2 b - - 3 33","moves":"a4d1 g5f7","rating":1033,"ratingDeviation":90,"randomNumberQuery":966,"popularity":47,"nbPlays":119,"themes":["mate","mateIn1","middlegame","oneMove","smotheredMate"],"gameUrl":"https://lichess.org/juj129gJ/black#65","openingFamily":"","openingVariation":"","__v":0},{"theme":"","_id":"65e8affaa5e6cd0e9b89e0fb","uid":"82nMM","fen":"4R3/1pp2ppk/p6p/5P2/8/P5Nn/1P4PP/R5qK w - - 7 30","moves":"a1g1 h3f2","rating":1023,"ratingDeviation":94,"randomNumberQuery":8897,"popularity":76,"nbPlays":151,"themes":["endgame","mate","mateIn1","oneMove","smotheredMate"],"gameUrl":"https://lichess.org/VkkTnG2w#58","openingFamily":"","openingVariation":"","__v":0},{"theme":"","_id":"65e8b0a4a5e6cd0e9b8c25fa","uid":"9GPkv","fen":"5rQk/pp4pp/2q2p1N/3p4/P2P4/1P3N2/7P/4R2K b - - 9 37","moves":"f8g8 h6f7","rating":1037,"ratingDeviation":89,"randomNumberQuery":5584,"popularity":84,"nbPlays":447,"themes":["endgame","mate","mateIn1","oneMove","smotheredMate"],"gameUrl":"https://lichess.org/ULfDpgZC/black#73","openingFamily":"","openingVariation":"","__v":0},{"theme":"","_id":"65e8b0cea5e6cd0e9b8cb3b2","uid":"9YuvR","fen":"r1bqkb1r/pppp1ppp/5n2/4p3/2PnP3/2N3P1/PP1P1P1P/R1BQKBNR w KQkq - 1 5","moves":"g1e2 d4f3","rating":1032,"ratingDeviation":89,"randomNumberQuery":8889,"popularity":81,"nbPlays":258,"themes":["mate","mateIn1","oneMove","opening","smotheredMate"],"gameUrl":"https://lichess.org/MMG3qJ4i#8","openingFamily":"","openingVariation":"","__v":0},{"theme":"","_id":"65e8b136a5e6cd0e9b8e281a","uid":"ALKH2","fen":"5rQk/p5pp/7N/8/3qN3/7P/PP3PP1/6K1 b - - 9 26","moves":"f8g8 h6f7","rating":1023,"ratingDeviation":107,"randomNumberQuery":3119,"popularity":44,"nbPlays":39,"themes":["endgame","mate","mateIn1","oneMove","smotheredMate"],"gameUrl":"https://lichess.org/4Aq2mn7F/black#51","openingFamily":"","openingVariation":"","__v":0},{"theme":"","_id":"65e8b15ba5e6cd0e9b8eac90","uid":"AcsVr","fen":"r3r1Qk/6pp/bp5N/p1b2R2/7B/2n5/P5PP/3R3K b - - 8 27","moves":"e8g8 h6f7","rating":1030,"ratingDeviation":76,"randomNumberQuery":6992,"popularity":98,"nbPlays":1216,"themes":["mate","mateIn1","middlegame","oneMove","smotheredMate"],"gameUrl":"https://lichess.org/8i0qxv4d/black#53","openingFamily":"","openingVariation":"","__v":0},{"theme":"","_id":"65e8b18ea5e6cd0e9b8f630c","uid":"B0hfg","fen":"1nkr3r/bppb2p1/5B2/1P6/2N4p/1N3P2/4R1PP/2R4K b - - 0 27","moves":"g7f6 c4d6","rating":1029,"ratingDeviation":144,"randomNumberQuery":5253,"popularity":65,"nbPlays":79,"themes":["mate","mateIn1","middlegame","oneMove","pin","smotheredMate"],"gameUrl":"https://lichess.org/9NskmWyU/black#53","openingFamily":"","openingVariation":"","__v":0},{"theme":"","_id":"65e8b194a5e6cd0e9b8f751c","uid":"B32qN","fen":"r4rkn/p4ppp/2p1p3/q2NP2P/1bP2P2/1P3NP1/P1bB3K/R3QR2 b - - 0 18","moves":"b4d2 d5e7","rating":1021,"ratingDeviation":79,"randomNumberQuery":6757,"popularity":94,"nbPlays":913,"themes":["mate","mateIn1","middlegame","oneMove","smotheredMate"],"gameUrl":"https://lichess.org/UO7Q1VbO/black#35","openingFamily":"Caro-Kann_Defense","openingVariation":"Caro-Kann_Defense_Other_variations","__v":0},{"theme":"","_id":"65e8b1a4a5e6cd0e9b8fa75a","uid":"B9eZe","fen":"r6r/1b3kpp/p2b4/1p6/3N1P2/3P2Nn/P1P3PP/R2QR1qK w - - 9 26","moves":"e1g1 h3f2","rating":1026,"ratingDeviation":82,"randomNumberQuery":1097,"popularity":100,"nbPlays":80,"themes":["mate","mateIn1","middlegame","oneMove","smotheredMate"],"gameUrl":"https://lichess.org/5lnOr849#50","openingFamily":"","openingVariation":"","__v":0},{"theme":"","_id":"65e8b1aaa5e6cd0e9b8fbeda","uid":"BCiGD","fen":"r1b1k1nr/pp1pppbp/6p1/q1p5/2PnP3/2NP2P1/PP2NP1P/R1BQKB1R w KQkq - 3 7","moves":"c1d2 d4f3","rating":1033,"ratingDeviation":78,"randomNumberQuery":4590,"popularity":94,"nbPlays":1487,"themes":["mate","mateIn1","oneMove","opening","smotheredMate"],"gameUrl":"https://lichess.org/ileQrdCm#12","openingFamily":"","openingVariation":"","__v":0},{"theme":"","_id":"65e8b1b4a5e6cd0e9b8fde8c","uid":"BGrLL","fen":"4rrQk/pb4pp/1p6/4Np2/1PB5/P3P3/1q3PPP/R4RK1 b - - 4 23","moves":"f8g8 e5f7","rating":1031,"ratingDeviation":81,"randomNumberQuery":2257,"popularity":54,"nbPlays":83,"themes":["mate","mateIn1","middlegame","oneMove","smotheredMate"],"gameUrl":"https://lichess.org/1T8iBGQO/black#45","openingFamily":"","openingVariation":"","__v":0},{"theme":"","_id":"65e8b1c0a5e6cd0e9b9006a0","uid":"BLzmO","fen":"5rk1/1bQ3pp/pN6/3pp3/1R6/2P2P1n/PP4PP/5RqK w - - 9 34","moves":"f1g1 h3f2","rating":1029,"ratingDeviation":184,"randomNumberQuery":6287,"popularity":25,"nbPlays":19,"themes":["mate","mateIn1","middlegame","oneMove","smotheredMate"],"gameUrl":"https://lichess.org/2yu1MO6W#66","openingFamily":"","openingVariation":"","__v":0},{"theme":"","_id":"65e8b1d5a5e6cd0e9b904cf4","uid":"BV67l","fen":"r2qkb1r/pb1pnppp/1pn1p3/1Np5/2B1PB2/3P1N2/PPP2PPP/R2QK2R b KQkq - 5 7","moves":"a8c8 b5d6","rating":1020,"ratingDeviation":80,"randomNumberQuery":8500,"popularity":90,"nbPlays":1103,"themes":["mate","mateIn1","oneMove","opening","smotheredMate"],"gameUrl":"https://lichess.org/rrRQMgTN/black#13","openingFamily":"Sicilian_Defense","openingVariation":"Sicilian_Defense_Old_Sicilian","__v":0},{"theme":"","_id":"65e8b211a5e6cd0e9b912290","uid":"BxQ4L","fen":"N1bk3r/p3bppp/2Pp4/4p3/2p1P3/5N1n/P1PB2PP/R3R1qK w - - 6 23","moves":"e1g1 h3f2","rating":1038,"ratingDeviation":99,"randomNumberQuery":4669,"popularity":73,"nbPlays":148,"themes":["mate","mateIn1","middlegame","oneMove","smotheredMate"],"gameUrl":"https://lichess.org/gx27HiG7#44","openingFamily":"","openingVariation":"","__v":0},{"theme":"","_id":"65e8b267a5e6cd0e9b924b76","uid":"CZsv1","fen":"r3r1Qk/p3B1bp/1p1P2pN/5p1q/4P1n1/5N2/PP3PPP/R3R1K1 b - - 6 22","moves":"e8g8 h6f7","rating":1020,"ratingDeviation":164,"randomNumberQuery":7666,"popularity":33,"nbPlays":57,"themes":["mate","mateIn1","middlegame","oneMove","smotheredMate"],"gameUrl":"https://lichess.org/ryRP7mFD/black#43","openingFamily":"","openingVariation":"","__v":0},{"theme":"","_id":"65e8b2a4a5e6cd0e9b931ffe","uid":"D1jRU","fen":"r3r1Qk/1p1bB1bp/1qnP2pN/p7/P7/1P2P3/6PP/2R2RK1 b - - 9 25","moves":"e8g8 h6f7","rating":1035,"ratingDeviation":75,"randomNumberQuery":3484,"popularity":100,"nbPlays":438,"themes":["mate","mateIn1","middlegame","oneMove","smotheredMate"],"gameUrl":"https://lichess.org/Cv39uA61/black#49","openingFamily":"","openingVariation":"","__v":0},{"theme":"","_id":"65e8b326a5e6cd0e9b94d370","uid":"DwjFg","fen":"3r1rk1/pp3ppp/8/7N/8/P1N2P1n/BP4PP/1R3RqK w - - 7 25","moves":"f1g1 h3f2","rating":1025,"ratingDeviation":80,"randomNumberQuery":3642,"popularity":87,"nbPlays":189,"themes":["mate","mateIn1","middlegame","oneMove","smotheredMate"],"gameUrl":"https://lichess.org/0eEvnWAk#48","openingFamily":"","openingVariation":"","__v":0},{"theme":"","_id":"65e8b342a5e6cd0e9b952f7b","uid":"E8rpk","fen":"1k3r2/pp4p1/8/8/3p4/n6p/PP5P/KqR2R2 w - - 6 36","moves":"c1b1 a3c2","rating":1038,"ratingDeviation":82,"randomNumberQuery":763,"popularity":85,"nbPlays":282,"themes":["endgame","mate","mateIn1","oneMove","smotheredMate"],"gameUrl":"https://lichess.org/Xfa5VLE8#70","openingFamily":"","openingVariation":"","__v":0},{"theme":"","_id":"65e8b384a5e6cd0e9b960335","uid":"EaYnb","fen":"r3kb1r/pp1npppp/2p2n2/qN3b2/2B5/3P4/PPPBQPPP/R3K1NR b KQkq - 6 8","moves":"a5d8 b5d6","rating":1038,"ratingDeviation":90,"randomNumberQuery":2767,"popularity":92,"nbPlays":1946,"themes":["master","mate","mateIn1","oneMove","opening","pin","smotheredMate"],"gameUrl":"https://lichess.org/BSoE7rsA/black#15","openingFamily":"","openingVariation":"","__v":0},{"theme":"","_id":"65e8b3e2a5e6cd0e9b974d93","uid":"FHoFK","fen":"r3r1Qk/ppp3pp/2n3nN/4p3/2Pp1Pq1/P2B2P1/1P3P1P/2KR3R b - - 7 21","moves":"e8g8 h6f7","rating":1026,"ratingDeviation":75,"randomNumberQuery":8176,"popularity":100,"nbPlays":127,"themes":["mate","mateIn1","middlegame","oneMove","smotheredMate"],"gameUrl":"https://lichess.org/uopnnWRi/black#41","openingFamily":"","openingVariation":"","__v":0},{"theme":"","_id":"65e8b46ea5e6cd0e9b993cb3","uid":"GKb2E","fen":"kQ1r2nr/pp4pp/4B3/1Nb2p1b/3pPB1q/5P2/PPP4P/R3R1K1 b - - 4 18","moves":"d8b8 b5c7","rating":1029,"ratingDeviation":95,"randomNumberQuery":6275,"popularity":58,"nbPlays":201,"themes":["mate","mateIn1","middlegame","oneMove","smotheredMate"],"gameUrl":"https://lichess.org/n9SEArNC/black#35","openingFamily":"Philidor_Defense","openingVariation":"Philidor_Defense_Other_variations","__v":0},{"theme":"","_id":"65e8b4b1a5e6cd0e9b9a2bd3","uid":"GprE7","fen":"r2qkb1r/1p1bnppp/2npp3/pNp5/2B1PP2/3P1N2/PPP3PP/R1B1QRK1 b kq - 1 9","moves":"c6a7 b5d6","rating":1026,"ratingDeviation":75,"randomNumberQuery":2887,"popularity":97,"nbPlays":1082,"themes":["mate","mateIn1","oneMove","opening","smotheredMate"],"gameUrl":"https://lichess.org/UAIa40pk/black#17","openingFamily":"Sicilian_Defense","openingVariation":"Sicilian_Defense_Closed","__v":0},{"theme":"","_id":"65e8b4c8a5e6cd0e9b9a7f11","uid":"H0ipj","fen":"r1b1kbnr/ppp1qppp/8/4n3/2Pp4/P4N2/1P1NPPPP/R1BQKB1R w KQkq - 0 7","moves":"f3d4 e5d3","rating":1030,"ratingDeviation":80,"randomNumberQuery":6161,"popularity":94,"nbPlays":549,"themes":["mate","mateIn1","oneMove","opening","pin","smotheredMate"],"gameUrl":"https://lichess.org/bFAdfzsS#12","openingFamily":"Queens_Gambit_Declined","openingVariation":"Queens_Gambit_Declined_Albin_Countergambit","__v":0},{"theme":"","_id":"65e8b4eda5e6cd0e9b9b024b","uid":"HI5IQ","fen":"r4rQk/6bp/6pN/4Pp2/p4P2/1p1R4/q5PP/3R3K b - - 6 36","moves":"f8g8 h6f7","rating":1022,"ratingDeviation":79,"randomNumberQuery":5950,"popularity":90,"nbPlays":118,"themes":["mate","mateIn1","middlegame","oneMove","smotheredMate"],"gameUrl":"https://lichess.org/nRvRHOsQ/black#71","openingFamily":"","openingVariation":"","__v":0},{"theme":"","_id":"65e8b4fea5e6cd0e9b9b403b","uid":"HQE7j","fen":"r4rk1/p2N2pp/2p5/3p4/Q7/2P4n/P5PP/R1R3qK w - - 4 24","moves":"c1g1 h3f2","rating":1024,"ratingDeviation":85,"randomNumberQuery":5004,"popularity":73,"nbPlays":140,"themes":["mate","mateIn1","middlegame","oneMove","smotheredMate"],"gameUrl":"https://lichess.org/GURZehkh#46","openingFamily":"","openingVariation":"","__v":0},{"theme":"","_id":"65e8b53aa5e6cd0e9b9c1803","uid":"HsVUC","fen":"r2qkb1r/pp1nnppp/4p3/1N1pP2b/2Pp4/5N1P/PP2BPP1/R1BQ1RK1 b kq - 1 10","moves":"h5f3 b5d6","rating":1039,"ratingDeviation":86,"randomNumberQuery":3757,"popularity":83,"nbPlays":607,"themes":["mate","mateIn1","oneMove","opening","smotheredMate"],"gameUrl":"https://lichess.org/WDLWKn6k/black#19","openingFamily":"Caro-Kann_Defense","openingVariation":"Caro-Kann_Defense_Other_variations","__v":0},{"theme":"","_id":"65e8b5c5a5e6cd0e9b9dff9c","uid":"ItuFH","fen":"r3kb1r/pp3ppp/2b1p3/2p1P1N1/2P5/1Q5n/PP1P2PP/RNB2RqK w kq - 8 16","moves":"f1g1 h3f2","rating":1028,"ratingDeviation":76,"randomNumberQuery":1072,"popularity":100,"nbPlays":313,"themes":["mate","mateIn1","oneMove","opening","smotheredMate"],"gameUrl":"https://lichess.org/JH30z1LZ#30","openingFamily":"Sicilian_Defense","openingVariation":"Sicilian_Defense_McDonnell_Attack","__v":0},{"theme":"","_id":"65e8b6aaa5e6cd0e9ba13184","uid":"KdHPv","fen":"r1bqkb1r/p2pnppp/1pn1p3/1N6/2P2B2/8/PP2PPPP/R2QKBNR b KQkq - 3 7","moves":"e6e5 b5d6","rating":1039,"ratingDeviation":78,"randomNumberQuery":5420,"popularity":94,"nbPlays":706,"themes":["mate","mateIn1","oneMove","opening","smotheredMate"],"gameUrl":"https://lichess.org/WYL8r5u2/black#13","openingFamily":"Horwitz_Defense","openingVariation":"Horwitz_Defense_Other_variations","__v":0},{"theme":"","_id":"65e8b6b0a5e6cd0e9ba148da","uid":"KgJc7","fen":"2B3k1/pp3pp1/1p1p3p/3P4/4P3/7n/P5PP/R3R1qK w - - 4 28","moves":"e1g1 h3f2","rating":1024,"ratingDeviation":155,"randomNumberQuery":2930,"popularity":76,"nbPlays":72,"themes":["endgame","mate","mateIn1","oneMove","smotheredMate"],"gameUrl":"https://lichess.org/NJcMneyN#54","openingFamily":"","openingVariation":"","__v":0},{"theme":"","_id":"65e8b6c8a5e6cd0e9ba19bea","uid":"KrJFp","fen":"r1b1r3/6kp/p2p2p1/1p1N4/4P3/3B3n/PPP3PP/R2QR1qK w - - 8 22","moves":"e1g1 h3f2","rating":1035,"ratingDeviation":92,"randomNumberQuery":7064,"popularity":58,"nbPlays":194,"themes":["mate","mateIn1","middlegame","oneMove","smotheredMate"],"gameUrl":"https://lichess.org/02jpO3j3#42","openingFamily":"","openingVariation":"","__v":0},{"theme":"","_id":"65e8b719a5e6cd0e9ba2b84d","uid":"LSqwY","fen":"Q3nrk1/p5bp/3pp1p1/6N1/2b2P2/2N4n/PPB3PP/R1BR2qK w - - 7 23","moves":"d1g1 h3f2","rating":1031,"ratingDeviation":84,"randomNumberQuery":1586,"popularity":84,"nbPlays":221,"themes":["mate","mateIn1","middlegame","oneMove","smotheredMate"],"gameUrl":"https://lichess.org/2ne1xJps#44","openingFamily":"","openingVariation":"","__v":0},{"theme":"","_id":"65e8b78fa5e6cd0e9ba44d75","uid":"MJgZJ","fen":"kQ1r4/pp3R2/N7/2p3p1/q1P3N1/7P/PP6/7K b - - 6 31","moves":"d8b8 a6c7","rating":1022,"ratingDeviation":75,"randomNumberQuery":6588,"popularity":98,"nbPlays":2971,"themes":["endgame","mate","mateIn1","oneMove","smotheredMate"],"gameUrl":"https://lichess.org/gM3HdEaF/black#61","openingFamily":"","openingVariation":"","__v":0},{"theme":"","_id":"65e8b798a5e6cd0e9ba4706b","uid":"MOI3c","fen":"8/p5qk/2Q4p/5p2/2P2Pn1/3P4/6PP/6NK w - - 3 46","moves":"c4c5 g4f2","rating":1020,"ratingDeviation":120,"randomNumberQuery":1492,"popularity":41,"nbPlays":71,"themes":["endgame","mate","mateIn1","oneMove","smotheredMate"],"gameUrl":"https://lichess.org/PJ2CM1SY#90","openingFamily":"","openingVariation":"","__v":0},{"theme":"","_id":"65e8b7bea5e6cd0e9ba4f5cf","uid":"MfYn7","fen":"1k1r4/pp3Q2/5p2/2b5/Pq1pNPn1/1P6/1BP3PP/6RK w - - 13 30","moves":"e4c5 g4f2","rating":1023,"ratingDeviation":127,"randomNumberQuery":4484,"popularity":54,"nbPlays":99,"themes":["mate","mateIn1","middlegame","oneMove","smotheredMate"],"gameUrl":"https://lichess.org/Uwyshfl4#58","openingFamily":"","openingVariation":"","__v":0},{"theme":"","_id":"65e8b7dba5e6cd0e9ba55c17","uid":"Msw5F","fen":"4r1k1/pp3p1p/2pN2p1/8/3q1Pn1/2Q5/PPP3PP/7K w - - 0 28","moves":"c3d4 e8e1 d4g1 g4f2","rating":1020,"ratingDeviation":75,"randomNumberQuery":6651,"popularity":95,"nbPlays":9146,"themes":["endgame","mate","mateIn2","pin","short","smotheredMate"],"gameUrl":"https://lichess.org/VwSfBxoY#54","openingFamily":"","openingVariation":"","__v":0},{"theme":"","_id":"65e8b822a5e6cd0e9ba65789","uid":"NPlTR","fen":"3rr1Qk/1p4np/1q5N/2b5/1p1p4/3P3P/P2B1PP1/R3R1K1 b - - 6 28","moves":"e8g8 h6f7","rating":1033,"ratingDeviation":162,"randomNumberQuery":2960,"popularity":53,"nbPlays":61,"themes":["mate","mateIn1","middlegame","oneMove","smotheredMate"],"gameUrl":"https://lichess.org/dP7HKGuX/black#55","openingFamily":"","openingVariation":"","__v":0},{"theme":"","_id":"65e8b833a5e6cd0e9ba6939f","uid":"NXm96","fen":"r2qkb1r/p2bnppp/4p3/1NppP3/5P2/3BB3/PPP3PP/R2Q1RK1 b kq - 1 13","moves":"c5c4 b5d6","rating":1026,"ratingDeviation":84,"randomNumberQuery":9875,"popularity":93,"nbPlays":91,"themes":["mate","mateIn1","oneMove","opening","smotheredMate"],"gameUrl":"https://lichess.org/09nAPwAK/black#25","openingFamily":"Sicilian_Defense","openingVariation":"Sicilian_Defense_Classical_Variation","__v":0},{"theme":"","_id":"65e8b84aa5e6cd0e9ba6e4e1","uid":"NiMSZ","fen":"3rkb1r/1b3ppp/p3p3/1p6/5P2/1Q3B1n/PP4PP/RNB1R1qK w k - 6 19","moves":"e1g1 h3f2","rating":1029,"ratingDeviation":99,"randomNumberQuery":1553,"popularity":69,"nbPlays":135,"themes":["mate","mateIn1","oneMove","opening","smotheredMate"],"gameUrl":"https://lichess.org/pEboIcKt#36","openingFamily":"Sicilian_Defense","openingVariation":"Sicilian_Defense_Old_Sicilian","__v":0},{"theme":"","_id":"65e8b88ba5e6cd0e9ba7cf53","uid":"ODBLO","fen":"4Qb1k/p5pp/2p2q2/3p4/6n1/2N4N/PPPB2PP/7K w - - 2 25","moves":"d2g5 f6f1 h3g1 g4f2","rating":1036,"ratingDeviation":83,"randomNumberQuery":2913,"popularity":94,"nbPlays":278,"themes":["mate","mateIn2","middlegame","short","smotheredMate"],"gameUrl":"https://lichess.org/A1SPr4qX#48","openingFamily":"","openingVariation":"","__v":0},{"theme":"","_id":"65e8b902a5e6cd0e9ba97614","uid":"P614Q","fen":"rnbqkbnr/pppp1p1p/8/3NP1p1/3P1p1P/8/PPP1Q1P1/R1B1KBNR b KQkq - 0 8","moves":"g8e7 d5f6","rating":1034,"ratingDeviation":78,"randomNumberQuery":3207,"popularity":94,"nbPlays":318,"themes":["mate","mateIn1","oneMove","opening","smotheredMate"],"gameUrl":"https://lichess.org/96YEQ9WP/black#15","openingFamily":"Vienna_Game","openingVariation":"Vienna_Game_Vienna_Gambit","__v":0},{"theme":"","_id":"65e8b928a5e6cd0e9ba9fb36","uid":"PNZX1","fen":"r1bqk2r/pppp2pp/5n2/2b1pp2/1nP5/1PN1P3/PB1PNPPP/R2QKB1R w KQkq - 5 7","moves":"a2a3 b4d3","rating":1031,"ratingDeviation":91,"randomNumberQuery":4232,"popularity":86,"nbPlays":341,"themes":["mate","mateIn1","oneMove","opening","smotheredMate"],"gameUrl":"https://lichess.org/N2cdHFaP#12","openingFamily":"","openingVariation":"","__v":0},{"theme":"","_id":"65e8b971a5e6cd0e9baafeb2","uid":"PvYVI","fen":"8/2p3pk/Q5pp/4p3/1P2P3/P1P3Pn/3r2BP/5RqK w - - 3 33","moves":"f1g1 h3f2","rating":1030,"ratingDeviation":82,"randomNumberQuery":3729,"popularity":92,"nbPlays":856,"themes":["endgame","mate","mateIn1","oneMove","smotheredMate"],"gameUrl":"https://lichess.org/dogDoDB3#64","openingFamily":"","openingVariation":"","__v":0},{"theme":"","_id":"65e8b9a4a5e6cd0e9babb61a","uid":"QJlvk","fen":"2rr2Qk/pb1n2bp/1pn3pN/8/3P4/PP6/1B3PPP/2R3K1 b - - 11 25","moves":"d8g8 h6f7","rating":1022,"ratingDeviation":83,"randomNumberQuery":9739,"popularity":100,"nbPlays":74,"themes":["mate","mateIn1","middlegame","oneMove","smotheredMate"],"gameUrl":"https://lichess.org/res40vzg/black#49","openingFamily":"","openingVariation":"","__v":0},{"theme":"","_id":"65e8b9ada5e6cd0e9babd186","uid":"QNKTi","fen":"r3k1nr/ppp1qppp/8/4n3/1bPp2b1/PP6/1B1NPPPP/RN1QKB1R w KQkq - 1 9","moves":"a3b4 e5d3","rating":1026,"ratingDeviation":88,"randomNumberQuery":6947,"popularity":92,"nbPlays":584,"themes":["mate","mateIn1","oneMove","opening","pin","smotheredMate"],"gameUrl":"https://lichess.org/Uu9MoazI#16","openingFamily":"","openingVariation":"","__v":0},{"theme":"","_id":"65e8b9b7a5e6cd0e9babf6f0","uid":"QSJUW","fen":"r1b2rQk/ppqp2bp/3N1pp1/8/2B2P1B/8/PPP3PP/2K4R b - - 4 19","moves":"f8g8 d6f7","rating":1027,"ratingDeviation":97,"randomNumberQuery":5231,"popularity":71,"nbPlays":154,"themes":["mate","mateIn1","middlegame","oneMove","smotheredMate"],"gameUrl":"https://lichess.org/8dWjibot/black#37","openingFamily":"Sicilian_Defense","openingVariation":"Sicilian_Defense_Hyperaccelerated_Fianchetto","__v":0},{"theme":"","_id":"65e8b9b9a5e6cd0e9babfd72","uid":"QTANi","fen":"5r1k/pp1b2pp/2p5/3p2Q1/8/P2P2Nn/BPP3PP/1R4qK w - - 6 24","moves":"b1g1 h3f2","rating":1032,"ratingDeviation":89,"randomNumberQuery":576,"popularity":78,"nbPlays":475,"themes":["mate","mateIn1","middlegame","oneMove","smotheredMate"],"gameUrl":"https://lichess.org/i0zhvzAf#46","openingFamily":"","openingVariation":"","__v":0},{"theme":"","_id":"65e8b9dea5e6cd0e9bac807b","uid":"QkBq0","fen":"r4rk1/pQ3ppp/2p1p3/8/2P5/P6n/1P4PP/R4RqK w - - 6 27","moves":"f1g1 h3f2","rating":1033,"ratingDeviation":96,"randomNumberQuery":2507,"popularity":73,"nbPlays":125,"themes":["endgame","mate","mateIn1","oneMove","smotheredMate"],"gameUrl":"https://lichess.org/aTBJrjck#52","openingFamily":"","openingVariation":"","__v":0},{"theme":"","_id":"65e8ba1da5e6cd0e9bad5edd","uid":"RDGN5","fen":"r1b2r1k/pp3Bpp/8/2p5/8/1Q5n/PP4PP/RN3RqK w - - 6 18","moves":"f1g1 h3f2","rating":1031,"ratingDeviation":89,"randomNumberQuery":4558,"popularity":82,"nbPlays":480,"themes":["mate","mateIn1","middlegame","oneMove","smotheredMate"],"gameUrl":"https://lichess.org/tqMyWC0n#34","openingFamily":"Bird_Opening","openingVariation":"Bird_Opening_Froms_Gambit","__v":0},{"theme":"","_id":"65e8ba54a5e6cd0e9bae20ad","uid":"RcboV","fen":"r3r1k1/5pbp/3p1np1/pp1P2B1/2p1PP2/PPN4n/2QN2PP/R3R1qK w - - 5 22","moves":"e1g1 h3f2","rating":1031,"ratingDeviation":87,"randomNumberQuery":9081,"popularity":67,"nbPlays":360,"themes":["mate","mateIn1","middlegame","oneMove","smotheredMate"],"gameUrl":"https://lichess.org/ZHCIYuK0#42","openingFamily":"","openingVariation":"","__v":0},{"theme":"","_id":"65e8ba6ca5e6cd0e9bae73f1","uid":"Rnh2S","fen":"r4rk1/4bppp/p1Q5/1p3N2/P7/7n/4B1PP/2RR2qK w - - 6 27","moves":"d1g1 h3f2","rating":1025,"ratingDeviation":88,"randomNumberQuery":5027,"popularity":56,"nbPlays":284,"themes":["mate","mateIn1","middlegame","oneMove","smotheredMate"],"gameUrl":"https://lichess.org/lrO4uAoC#52","openingFamily":"","openingVariation":"","__v":0},{"theme":"","_id":"65e8bac6a5e6cd0e9bafb2f9","uid":"ST0uC","fen":"r2q1rk1/4b1pp/p4np1/1pp5/1nPpp1P1/NP2P2P/PB1P1PB1/1QKR3R w - - 0 17","moves":"a3c2 b4d3","rating":1035,"ratingDeviation":76,"randomNumberQuery":8275,"popularity":100,"nbPlays":171,"themes":["mate","mateIn1","middlegame","oneMove","smotheredMate"],"gameUrl":"https://lichess.org/Rf7ndXpW#32","openingFamily":"Nimzo-Larsen_Attack","openingVariation":"Nimzo-Larsen_Attack_Classical_Variation","__v":0},{"theme":"","_id":"65e8bb12a5e6cd0e9bb0bc73","uid":"T1ovq","fen":"6k1/3Q1p2/p5pp/1p1p4/1P6/P1r4n/6PP/5RqK w - - 6 36","moves":"f1g1 h3f2","rating":1025,"ratingDeviation":88,"randomNumberQuery":401,"popularity":56,"nbPlays":315,"themes":["endgame","mate","mateIn1","oneMove","smotheredMate"],"gameUrl":"https://lichess.org/WcB2b3fz#70","openingFamily":"","openingVariation":"","__v":0},{"theme":"","_id":"65e8bb1aa5e6cd0e9bb0da8b","uid":"T5gYh","fen":"r1bqkbnr/1p1p1p1p/2n3p1/p1pNp3/4P3/P2P1N2/1PPB1PPP/R2QKB1R b KQkq - 0 7","moves":"g8e7 d5f6","rating":1031,"ratingDeviation":89,"randomNumberQuery":1012,"popularity":86,"nbPlays":404,"themes":["mate","mateIn1","oneMove","opening","smotheredMate"],"gameUrl":"https://lichess.org/3FvlygXw/black#13","openingFamily":"","openingVariation":"","__v":0},{"theme":"","_id":"65e8bb21a5e6cd0e9bb0f33f","uid":"T8uRJ","fen":"rq3rQk/pp1b2bp/3N2p1/4p1P1/1n1p1P1P/1B1P4/PP6/R1B2RK1 b - - 5 23","moves":"f8g8 d6f7","rating":1025,"ratingDeviation":113,"randomNumberQuery":5197,"popularity":62,"nbPlays":128,"themes":["mate","mateIn1","middlegame","oneMove","smotheredMate"],"gameUrl":"https://lichess.org/9olM913C/black#45","openingFamily":"","openingVariation":"","__v":0},{"theme":"","_id":"65e8bb44a5e6cd0e9bb16dbb","uid":"TOwTd","fen":"r4r2/3Q2pk/p1R4p/1p3N2/3P4/1P5n/1PP3PP/5RqK w - - 5 35","moves":"f1g1 h3f2","rating":1033,"ratingDeviation":97,"randomNumberQuery":7703,"popularity":78,"nbPlays":238,"themes":["mate","mateIn1","middlegame","oneMove","smotheredMate"],"gameUrl":"https://lichess.org/YXRwQXt0#68","openingFamily":"","openingVariation":"","__v":0},{"theme":"","_id":"65e8bb59a5e6cd0e9bb1b945","uid":"TYeV0","fen":"r3r1Qk/p5pp/1p5N/n4b2/5B2/qP2P1P1/P4PBP/5RK1 b - - 5 24","moves":"e8g8 h6f7","rating":1026,"ratingDeviation":105,"randomNumberQuery":2148,"popularity":69,"nbPlays":201,"themes":["kingsideAttack","mate","mateIn1","middlegame","oneMove","smotheredMate"],"gameUrl":"https://lichess.org/GzsuAHxl/black#47","openingFamily":"","openingVariation":"","__v":0},{"theme":"","_id":"65e8bba0a5e6cd0e9bb2b334","uid":"U5EnF","fen":"r4rk1/pp2pp2/3p2pQ/7p/2P4P/n3P3/PP2B3/Kq1R2R1 w - - 6 24","moves":"d1b1 a3c2","rating":1027,"ratingDeviation":90,"randomNumberQuery":9700,"popularity":73,"nbPlays":317,"themes":["mate","mateIn1","middlegame","oneMove","smotheredMate"],"gameUrl":"https://lichess.org/puASDFZd#46","openingFamily":"","openingVariation":"","__v":0},{"theme":"","_id":"65e8bbb7a5e6cd0e9bb30388","uid":"UFlyZ","fen":"rq2r1Qk/6bp/6pN/5p2/3p4/3P2PP/5P1K/4q3 b - - 5 36","moves":"e8g8 h6f7","rating":1028,"ratingDeviation":101,"randomNumberQuery":333,"popularity":75,"nbPlays":149,"themes":["endgame","mate","mateIn1","oneMove","smotheredMate"],"gameUrl":"https://lichess.org/sRlDp1Oh/black#71","openingFamily":"","openingVariation":"","__v":0},{"theme":"","_id":"65e8bbc0a5e6cd0e9bb32380","uid":"UK1rD","fen":"r2qkbnr/3n1pp1/p3p2p/2p1P3/P3N3/4PN2/1PPQ2PP/R3K2R b KQkq - 0 14","moves":"g8e7 e4d6","rating":1031,"ratingDeviation":86,"randomNumberQuery":7120,"popularity":88,"nbPlays":515,"themes":["mate","mateIn1","middlegame","oneMove","smotheredMate"],"gameUrl":"https://lichess.org/SAWSRV1Q/black#27","openingFamily":"Rat_Defense","openingVariation":"Rat_Defense_Small_Center_Defense","__v":0},{"theme":"","_id":"65e8bbe1a5e6cd0e9bb39573","uid":"UYz2M","fen":"r4Qkr/ppp2ppp/5nN1/7q/2B2p2/8/PPPB3P/2KR3b b - - 7 19","moves":"a8f8 g6e7","rating":1021,"ratingDeviation":78,"randomNumberQuery":5291,"popularity":93,"nbPlays":587,"themes":["mate","mateIn1","middlegame","oneMove","smotheredMate"],"gameUrl":"https://lichess.org/owiQtpuo/black#37","openingFamily":"","openingVariation":"","__v":0},{"theme":"","_id":"65e8bc1ca5e6cd0e9bb46831","uid":"V0UNM","fen":"r4rk1/ppp2ppp/2n5/2b4n/4P1bq/3P4/PPP1B1PP/RNBQ1RNK w - - 9 11","moves":"e2g4 h5g3","rating":1031,"ratingDeviation":80,"randomNumberQuery":5455,"popularity":65,"nbPlays":72,"themes":["mate","mateIn1","middlegame","oneMove","pin","smotheredMate"],"gameUrl":"https://lichess.org/ee76oU0k#20","openingFamily":"Bird_Opening","openingVariation":"Bird_Opening_Schlechter_Gambit","__v":0},{"theme":"","_id":"65e8bc1da5e6cd0e9bb46f1f","uid":"V1ND7","fen":"r1b2rQk/1p1n2pp/q6N/p3Pp2/3P1N2/6P1/PP5P/R1B2RK1 b - - 9 23","moves":"f8g8 h6f7","rating":1029,"ratingDeviation":90,"randomNumberQuery":1899,"popularity":74,"nbPlays":285,"themes":["master","mate","mateIn1","middlegame","oneMove","smotheredMate"],"gameUrl":"https://lichess.org/cIkvz8tP/black#45","openingFamily":"","openingVariation":"","__v":0},{"theme":"","_id":"65e8bc77a5e6cd0e9bb5a44e","uid":"Vfy7d","fen":"r1bqkbnr/3npppp/pp6/8/3PNB2/8/PP2QPPP/R3KBNR b KQkq - 3 8","moves":"c8b7 e4d6","rating":1028,"ratingDeviation":77,"randomNumberQuery":9920,"popularity":96,"nbPlays":1172,"themes":["mate","mateIn1","oneMove","opening","pin","smotheredMate"],"gameUrl":"https://lichess.org/xfh6bhUF/black#15","openingFamily":"Slav_Defense","openingVariation":"Slav_Defense_Exchange_Variation","__v":0},{"theme":"","_id":"65e8bc81a5e6cd0e9bb5c786","uid":"VkU3U","fen":"6qk/7r/4P3/3PQ3/2Pp1N2/8/PPK5/6q1 b - - 3 52","moves":"g1g7 f4g6","rating":1023,"ratingDeviation":84,"randomNumberQuery":4895,"popularity":89,"nbPlays":656,"themes":["endgame","mate","mateIn1","oneMove","pin","smotheredMate"],"gameUrl":"https://lichess.org/lQObUZ4w/black#103","openingFamily":"","openingVariation":"","__v":0},{"theme":"","_id":"65e8bcfba5e6cd0e9bb776ba","uid":"WelpR","fen":"r1b1kb1r/ppppqppp/5n2/4N3/2Pn4/2N3P1/PP1PPP1P/R1BQKB1R w KQkq - 1 6","moves":"e5f3 d4f3","rating":1033,"ratingDeviation":87,"randomNumberQuery":2254,"popularity":92,"nbPlays":2314,"themes":["mate","mateIn1","oneMove","opening","pin","smotheredMate"],"gameUrl":"https://lichess.org/mWhJVFYN#10","openingFamily":"","openingVariation":"","__v":0},{"theme":"","_id":"65e8bd3aa5e6cd0e9bb84f18","uid":"X7AtA","fen":"r3k2N/ppp4Q/2n1b3/4b3/8/3P1p1n/PPP3PP/RNB2RqK w q - 5 19","moves":"f1g1 h3f2","rating":1025,"ratingDeviation":81,"randomNumberQuery":2496,"popularity":86,"nbPlays":701,"themes":["mate","mateIn1","middlegame","oneMove","smotheredMate"],"gameUrl":"https://lichess.org/3Mx5XYs5#36","openingFamily":"Latvian_Gambit","openingVariation":"Latvian_Gambit_Other_variations","__v":0},{"theme":"","_id":"65e8bde8a5e6cd0e9bbaad91","uid":"YOOEX","fen":"r4Qkr/pp3ppp/2P3N1/2n5/2B2BP1/1R3K2/q6P/8 b - - 7 26","moves":"a8f8 g6e7","rating":1031,"ratingDeviation":78,"randomNumberQuery":981,"popularity":88,"nbPlays":677,"themes":["mate","mateIn1","middlegame","oneMove","smotheredMate"],"gameUrl":"https://lichess.org/t0uAasMI/black#51","openingFamily":"","openingVariation":"","__v":0},{"theme":"","_id":"65e8be31a5e6cd0e9bbbb0b5","uid":"Yw8ri","fen":"1r2r1Qk/bpp3pp/p5nN/2P5/3PPP1q/4B1NP/PP6/R4RK1 b - - 4 27","moves":"e8g8 h6f7","rating":1024,"ratingDeviation":85,"randomNumberQuery":2169,"popularity":100,"nbPlays":52,"themes":["mate","mateIn1","middlegame","oneMove","smotheredMate"],"gameUrl":"https://lichess.org/UmOKsYpk/black#53","openingFamily":"","openingVariation":"","__v":0},{"theme":"","_id":"65e8be4aa5e6cd0e9bbc0897","uid":"Z7dX6","fen":"r4rQk/6pp/nR3p1N/p7/8/P5B1/2P1p1PP/3qR2K b - - 7 36","moves":"f8g8 h6f7","rating":1036,"ratingDeviation":75,"randomNumberQuery":7253,"popularity":98,"nbPlays":1330,"themes":["mate","mateIn1","middlegame","oneMove","smotheredMate"],"gameUrl":"https://lichess.org/wgkEzITb/black#71","openingFamily":"","openingVariation":"","__v":0},{"theme":"","_id":"65e8be62a5e6cd0e9bbc5858","uid":"ZI4cI","fen":"r2q2rk/1b1p1pp1/ppn2n1p/2p2pN1/P1B1PB1Q/3P4/1PP3PP/R4RK1 b - - 1 16","moves":"f6h7 g5f7","rating":1028,"ratingDeviation":93,"randomNumberQuery":8972,"popularity":73,"nbPlays":156,"themes":["kingsideAttack","mate","mateIn1","middlegame","oneMove","smotheredMate"],"gameUrl":"https://lichess.org/HbUXW5s7/black#31","openingFamily":"Sicilian_Defense","openingVariation":"Sicilian_Defense_Closed","__v":0},{"theme":"","_id":"65e8be90a5e6cd0e9bbcf602","uid":"Zcawg","fen":"3rk2r/p1p2ppp/4P3/4p3/8/7n/PP4PP/RNBQ1RqK w k - 7 19","moves":"f1g1 h3f2","rating":1025,"ratingDeviation":159,"randomNumberQuery":6040,"popularity":50,"nbPlays":64,"themes":["mate","mateIn1","middlegame","oneMove","smotheredMate"],"gameUrl":"https://lichess.org/XGac6VIz#36","openingFamily":"","openingVariation":"","__v":0},{"theme":"","_id":"65e8be9da5e6cd0e9bbd2394","uid":"ZiWeC","fen":"2r1k1nr/1b2ppbp/p2p2p1/q1n3B1/1p2P1P1/P4P2/1PPQN2P/1NKR1B1R w k - 0 13","moves":"a3b4 c5b3","rating":1023,"ratingDeviation":76,"randomNumberQuery":8547,"popularity":96,"nbPlays":6756,"themes":["master","mate","mateIn1","middlegame","oneMove","pin","smotheredMate"],"gameUrl":"https://lichess.org/A1bYb29u#24","openingFamily":"Modern_Defense","openingVariation":"Modern_Defense_Standard_Defense","__v":0},{"theme":"","_id":"65e8bea3a5e6cd0e9bbd3958","uid":"ZlMNO","fen":"r4rQk/p1qn2pp/1pp4N/8/3P4/2P1PR2/P1P3PP/5RK1 b - - 4 21","moves":"f8g8 h6f7","rating":1027,"ratingDeviation":94,"randomNumberQuery":4567,"popularity":59,"nbPlays":266,"themes":["mate","mateIn1","middlegame","oneMove","smotheredMate"],"gameUrl":"https://lichess.org/HvTXawIP/black#41","openingFamily":"","openingVariation":"","__v":0},{"theme":"","_id":"65e8beb7a5e6cd0e9bbd7dfe","uid":"ZuOlu","fen":"2r2rQk/6pp/1q2B3/1p1nN3/2pP4/1n5P/1P3PP1/2R1R1K1 b - - 2 26","moves":"f8g8 e5f7","rating":1038,"ratingDeviation":77,"randomNumberQuery":9085,"popularity":80,"nbPlays":208,"themes":["mate","mateIn1","middlegame","oneMove","smotheredMate"],"gameUrl":"https://lichess.org/ttJFykwU/black#51","openingFamily":"","openingVariation":"","__v":0},{"theme":"","_id":"65e8bebfa5e6cd0e9bbd9926","uid":"Zxri3","fen":"6k1/pp3pbp/1n4p1/8/2P1Q1n1/1PN1PN2/PB4PP/5q1K w - - 7 25","moves":"f3g1 g4f2","rating":1022,"ratingDeviation":114,"randomNumberQuery":846,"popularity":73,"nbPlays":100,"themes":["mate","mateIn1","middlegame","oneMove","smotheredMate"],"gameUrl":"https://lichess.org/xdAzlzne#48","openingFamily":"","openingVariation":"","__v":0},{"theme":"","_id":"65e8bec4a5e6cd0e9bbdad9c","uid":"a0Xxh","fen":"r1bqkb1r/3nnpp1/2ppp2p/8/1p1PN3/4P1P1/PP1BNPBP/R2Q1RK1 b kq - 1 11","moves":"d6d5 e4d6","rating":1023,"ratingDeviation":85,"randomNumberQuery":4382,"popularity":75,"nbPlays":125,"themes":["mate","mateIn1","middlegame","oneMove","smotheredMate"],"gameUrl":"https://lichess.org/P7n0mQGM/black#21","openingFamily":"English_Opening","openingVariation":"English_Opening_Other_variations","__v":0},{"theme":"","_id":"65e8bed0a5e6cd0e9bbdd79c","uid":"a67d0","fen":"r3r1Qk/pbqn2bp/5npN/1p6/2BB1P2/1P6/P1PN2PP/R4RK1 b - - 4 17","moves":"e8g8 h6f7","rating":1038,"ratingDeviation":75,"randomNumberQuery":4219,"popularity":99,"nbPlays":911,"themes":["mate","mateIn1","middlegame","oneMove","smotheredMate"],"gameUrl":"https://lichess.org/zftepHQf/black#33","openingFamily":"Nimzo-Larsen_Attack","openingVariation":"Nimzo-Larsen_Attack_Indian_Variation","__v":0},{"theme":"","_id":"65e8beeca5e6cd0e9bbe3914","uid":"aIrAj","fen":"r3k1nr/p1b2p2/2pp1q1p/4p3/1n2P1b1/2NPBN2/1PPQBPP1/2KR3R w kq - 0 19","moves":"c3b1 b4a2","rating":1020,"ratingDeviation":83,"randomNumberQuery":3931,"popularity":81,"nbPlays":322,"themes":["mate","mateIn1","middlegame","oneMove","smotheredMate"],"gameUrl":"https://lichess.org/buXEnpRZ#36","openingFamily":"Kings_Pawn_Game","openingVariation":"Kings_Pawn_Game_McConnell_Defense","__v":0},{"theme":"","_id":"65e8bf1aa5e6cd0e9bbeda72","uid":"adxyv","fen":"3r1rk1/2p2bpp/1bp2pn1/p3pN1P/4P1P1/1N6/PPP2PK1/R1B2R2 b - - 0 17","moves":"g6h8 f5e7","rating":1032,"ratingDeviation":87,"randomNumberQuery":5808,"popularity":100,"nbPlays":58,"themes":["mate","mateIn1","middlegame","oneMove","smotheredMate"],"gameUrl":"https://lichess.org/8h5eeaEi/black#33","openingFamily":"Scotch_Game","openingVariation":"Scotch_Game_Other_variations","__v":0},{"theme":"","_id":"65e8bf42a5e6cd0e9bbf67e0","uid":"awHok","fen":"r2qkb1r/1b1p1ppp/p1n1pn2/1p3N2/8/2P5/PPB2PPP/RNBQR1K1 b kq - 2 11","moves":"c6e7 f5d6","rating":1031,"ratingDeviation":76,"randomNumberQuery":7766,"popularity":93,"nbPlays":1258,"themes":["mate","mateIn1","oneMove","opening","smotheredMate"],"gameUrl":"https://lichess.org/Gst4ROJX/black#21","openingFamily":"Sicilian_Defense","openingVariation":"Sicilian_Defense_Delayed_Alapin_Variation","__v":0},{"theme":"","_id":"65e8bf67a5e6cd0e9bbfecfc","uid":"bDmvf","fen":"4r1rk/1pp3bp/8/p3Np2/5P2/6BP/P2n1P2/1R3R1K b - - 2 27","moves":"d2f1 e5f7","rating":1032,"ratingDeviation":90,"randomNumberQuery":3936,"popularity":70,"nbPlays":174,"themes":["master","mate","mateIn1","middlegame","oneMove","smotheredMate"],"gameUrl":"https://lichess.org/qo44GcVm/black#53","openingFamily":"","openingVariation":"","__v":0},{"theme":"","_id":"65e8bf9ba5e6cd0e9bc0a726","uid":"bc6CJ","fen":"r3r1Qk/1bp3pp/3q1n2/4N3/3Pp3/p4P2/B5PP/2R1R1K1 b - - 2 26","moves":"f6g8 e5f7","rating":1023,"ratingDeviation":164,"randomNumberQuery":6446,"popularity":50,"nbPlays":57,"themes":["mate","mateIn1","middlegame","oneMove","smotheredMate"],"gameUrl":"https://lichess.org/Gj9eBtLu/black#51","openingFamily":"","openingVariation":"","__v":0},{"theme":"","_id":"65e8bfefa5e6cd0e9bc1d3e2","uid":"cFF4b","fen":"kQ1r2r1/pb2Np2/N4np1/8/8/5P2/qPP3P1/2KR3R b - - 8 25","moves":"d8b8 a6c7","rating":1024,"ratingDeviation":100,"randomNumberQuery":7638,"popularity":80,"nbPlays":200,"themes":["mate","mateIn1","middlegame","oneMove","queensideAttack","smotheredMate"],"gameUrl":"https://lichess.org/aLFi8EGc/black#49","openingFamily":"","openingVariation":"","__v":0},{"theme":"","_id":"65e8c00aa5e6cd0e9bc2317c","uid":"cRSc2","fen":"r5k1/2p3pp/p3P3/8/5B2/2N4n/PPP3PP/R5qK w - - 5 26","moves":"a1g1 h3f2","rating":1038,"ratingDeviation":76,"randomNumberQuery":33,"popularity":97,"nbPlays":545,"themes":["endgame","mate","mateIn1","oneMove","smotheredMate"],"gameUrl":"https://lichess.org/teLNuyd6#50","openingFamily":"","openingVariation":"","__v":0},{"theme":"","_id":"65e8c01aa5e6cd0e9bc26946","uid":"cYqsi","fen":"r4rnk/2qbb1pp/2n2p2/pp2pPPQ/2ppP2N/3P2NP/PPP3BK/R1B2R2 b - - 1 19","moves":"f6g5 h4g6","rating":1032,"ratingDeviation":86,"randomNumberQuery":6783,"popularity":87,"nbPlays":508,"themes":["mate","mateIn1","middlegame","oneMove","pin","smotheredMate"],"gameUrl":"https://lichess.org/3ASuiFoC/black#37","openingFamily":"Sicilian_Defense","openingVariation":"Sicilian_Defense_Closed","__v":0},{"theme":"","_id":"65e8c024a5e6cd0e9bc28d8e","uid":"cddZx","fen":"r4rk1/p1p2p1p/1p2p1p1/8/2NP2n1/P2QPq2/2B2PRP/6RK w - - 2 23","moves":"c4e5 g4f2","rating":1037,"ratingDeviation":97,"randomNumberQuery":9726,"popularity":80,"nbPlays":244,"themes":["kingsideAttack","mate","mateIn1","middlegame","oneMove","smotheredMate"],"gameUrl":"https://lichess.org/DoP4OXpN#44","openingFamily":"","openingVariation":"","__v":0},{"theme":"","_id":"65e8c032a5e6cd0e9bc2bfc8","uid":"ckB00","fen":"r2r2k1/pp3ppp/2nQb3/4p3/N7/P1P2NPn/1P2P1BP/R1B3qK w - - 8 17","moves":"f3g1 h3f2","rating":1036,"ratingDeviation":75,"randomNumberQuery":2047,"popularity":99,"nbPlays":670,"themes":["mate","mateIn1","middlegame","oneMove","smotheredMate"],"gameUrl":"https://lichess.org/SMzmIUr3#32","openingFamily":"Indian_Defense","openingVariation":"Indian_Defense_Knights_Variation","__v":0},{"theme":"","_id":"65e8c064a5e6cd0e9bc37418","uid":"d7fi5","fen":"r1bqk1nr/pp1p1pbp/4p1p1/2p5/2PnP3/2NP4/PP1BNPPP/R2QKB1R w KQkq - 0 7","moves":"g2g3 d4f3","rating":1036,"ratingDeviation":86,"randomNumberQuery":993,"popularity":83,"nbPlays":444,"themes":["mate","mateIn1","oneMove","opening","smotheredMate"],"gameUrl":"https://lichess.org/R3HqQjrp#12","openingFamily":"","openingVariation":"","__v":0},{"theme":"","_id":"65e8c077a5e6cd0e9bc3b464","uid":"dFwxJ","fen":"1n5r/pkN2ppp/1p6/8/1P3B2/2P4n/P5PP/3RR1qK w - - 5 27","moves":"e1g1 h3f2","rating":1027,"ratingDeviation":106,"randomNumberQuery":8877,"popularity":54,"nbPlays":118,"themes":["mate","mateIn1","middlegame","oneMove","smotheredMate"],"gameUrl":"https://lichess.org/z8IOt12D#52","openingFamily":"","openingVariation":"","__v":0},{"theme":"","_id":"65e8c07ba5e6cd0e9bc3beb3","uid":"dHH0D","fen":"5rQk/6pp/7N/3p4/P7/6P1/1q2NP1P/2b3K1 b - - 5 35","moves":"f8g8 h6f7","rating":1036,"ratingDeviation":100,"randomNumberQuery":5850,"popularity":71,"nbPlays":202,"themes":["endgame","mate","mateIn1","oneMove","smotheredMate"],"gameUrl":"https://lichess.org/we7Hj0Ls/black#69","openingFamily":"","openingVariation":"","__v":0},{"theme":"","_id":"65e8c07fa5e6cd0e9bc3ca6f","uid":"dInUr","fen":"5r1k/pp1r2pp/4p3/8/1PB5/1QP4n/P5PP/1R3RqK w - - 4 23","moves":"f1g1 h3f2","rating":1024,"ratingDeviation":76,"randomNumberQuery":2636,"popularity":92,"nbPlays":868,"themes":["mate","mateIn1","middlegame","oneMove","smotheredMate"],"gameUrl":"https://lichess.org/GgveeAHO#44","openingFamily":"","openingVariation":"","__v":0},{"theme":"","_id":"65e8c080a5e6cd0e9bc3d087","uid":"dJYxj","fen":"8/ppp1b2k/3pb1rp/4P3/5Qn1/2N5/PPP2PPq/4R1RK w - - 0 22","moves":"f4h2 g4f2","rating":1021,"ratingDeviation":88,"randomNumberQuery":1407,"popularity":73,"nbPlays":162,"themes":["kingsideAttack","mate","mateIn1","middlegame","oneMove","smotheredMate"],"gameUrl":"https://lichess.org/W7kLRuJE#42","openingFamily":"","openingVariation":"","__v":0},{"theme":"","_id":"65e8c0e3a5e6cd0e9bc52acb","uid":"e2k1X","fen":"2kr1bnr/ppp1qppp/8/4n3/2PN2b1/P5P1/1P1NPP1P/R1BQKB1R w KQ - 1 9","moves":"d4b3 e5d3","rating":1021,"ratingDeviation":75,"randomNumberQuery":6040,"popularity":95,"nbPlays":539,"themes":["mate","mateIn1","oneMove","opening","pin","smotheredMate"],"gameUrl":"https://lichess.org/sMo2i2As#16","openingFamily":"Queens_Gambit_Declined","openingVariation":"Queens_Gambit_Declined_Albin_Countergambit","__v":0},{"theme":"","_id":"65e8c0f2a5e6cd0e9bc55d7d","uid":"e9Rm4","fen":"5rkr/p1Q3pp/b1p5/3p4/8/5P1n/PPP3PP/RN2R1qK w - - 6 23","moves":"e1g1 h3f2","rating":1023,"ratingDeviation":89,"randomNumberQuery":9229,"popularity":74,"nbPlays":460,"themes":["mate","mateIn1","middlegame","oneMove","smotheredMate"],"gameUrl":"https://lichess.org/V0y1edfY#44","openingFamily":"","openingVariation":"","__v":0},{"theme":"","_id":"65e8c15ca5e6cd0e9bc6cac5","uid":"evIKt","fen":"r4rk1/pp4pp/5n2/5P2/2p1p3/1PN4n/P1QP2PP/R1B2RqK w - - 5 20","moves":"f1g1 h3f2","rating":1039,"ratingDeviation":99,"randomNumberQuery":2649,"popularity":54,"nbPlays":183,"themes":["mate","mateIn1","middlegame","oneMove","smotheredMate"],"gameUrl":"https://lichess.org/odTyFwEj#38","openingFamily":"","openingVariation":"","__v":0},{"theme":"","_id":"65e8c189a5e6cd0e9bc7661b","uid":"fFsRa","fen":"2brr1k1/pp3ppp/3b4/P4P2/2p3nN/1P1P1nP1/2PB2BP/R2QR1qK w - - 3 20","moves":"e1g1 g4f2","rating":1025,"ratingDeviation":83,"randomNumberQuery":280,"popularity":92,"nbPlays":667,"themes":["mate","mateIn1","middlegame","oneMove","smotheredMate"],"gameUrl":"https://lichess.org/b1WEoo91#38","openingFamily":"","openingVariation":"","__v":0},{"theme":"","_id":"65e8c192a5e6cd0e9bc78545","uid":"fK2DL","fen":"1r4Qk/1q1nR1bp/3p2pN/2p5/8/7P/1PP2PP1/2B3K1 b - - 6 24","moves":"b8g8 h6f7","rating":1037,"ratingDeviation":75,"randomNumberQuery":1955,"popularity":98,"nbPlays":994,"themes":["mate","mateIn1","middlegame","oneMove","smotheredMate"],"gameUrl":"https://lichess.org/FnJZwU3j/black#47","openingFamily":"","openingVariation":"","__v":0},{"theme":"","_id":"65e8c1f0a5e6cd0e9bc8c28e","uid":"fz5eN","fen":"2r2rk1/pp3ppp/8/8/Q1b5/PPN2N1n/6PP/RR4qK w - - 5 23","moves":"f3g1 h3f2","rating":1029,"ratingDeviation":94,"randomNumberQuery":2107,"popularity":74,"nbPlays":356,"themes":["mate","mateIn1","middlegame","oneMove","smotheredMate"],"gameUrl":"https://lichess.org/zvsF2dQA#44","openingFamily":"","openingVariation":"","__v":0},{"theme":"","_id":"65e8c1f4a5e6cd0e9bc8ced6","uid":"g0kJn","fen":"5rk1/pp4pb/7p/3pNp1Q/5P2/1P1B3n/P5PP/2R3qK w - - 6 28","moves":"c1g1 h3f2","rating":1028,"ratingDeviation":93,"randomNumberQuery":9427,"popularity":59,"nbPlays":202,"themes":["mate","mateIn1","middlegame","oneMove","smotheredMate"],"gameUrl":"https://lichess.org/ZkfYylme#54","openingFamily":"","openingVariation":"","__v":0},{"theme":"","_id":"65e8c23ea5e6cd0e9bc9ce1e","uid":"gYQ0D","fen":"5rk1/5ppp/4p3/4P3/2r1bB2/1Q5n/P5PP/R4RqK w - - 8 25","moves":"f1g1 h3f2","rating":1023,"ratingDeviation":80,"randomNumberQuery":8169,"popularity":64,"nbPlays":161,"themes":["mate","mateIn1","middlegame","oneMove","smotheredMate"],"gameUrl":"https://lichess.org/hv4jtOrf#48","openingFamily":"","openingVariation":"","__v":0},{"theme":"","_id":"65e8c241a5e6cd0e9bc9d8a0","uid":"gZkOk","fen":"3Q3r/p1pR4/5pk1/2q3pp/4n3/2P2N2/P1P2PPP/6K1 w - - 6 27","moves":"d8h8 c5f2 g1h1 f2f1 f3g1 e4f2","rating":1034,"ratingDeviation":74,"randomNumberQuery":7762,"popularity":96,"nbPlays":3201,"themes":["endgame","long","mate","mateIn3","smotheredMate"],"gameUrl":"https://lichess.org/0x3xeHWN#52","openingFamily":"","openingVariation":"","__v":0},{"theme":"","_id":"65e8c272a5e6cd0e9bca8222","uid":"gvter","fen":"r1bq1rk1/1pp2pbp/3p1np1/pPn5/2PNp3/P3P3/1B1PNPPP/R2QKB1R w KQ - 2 11","moves":"d4b3 c5d3","rating":1036,"ratingDeviation":87,"randomNumberQuery":5697,"popularity":75,"nbPlays":269,"themes":["master","mate","mateIn1","oneMove","opening","smotheredMate"],"gameUrl":"https://lichess.org/r74cqqbz#20","openingFamily":"Polish_Opening","openingVariation":"Polish_Opening_Bugayev_Attack","__v":0},{"theme":"","_id":"65e8c2a0a5e6cd0e9bcb2168","uid":"hGnGW","fen":"5r2/p5k1/5ppp/3B4/bP6/P6n/2r3PP/QR3RqK w - - 8 36","moves":"f1g1 h3f2","rating":1039,"ratingDeviation":198,"randomNumberQuery":5602,"popularity":47,"nbPlays":38,"themes":["mate","mateIn1","middlegame","oneMove","smotheredMate"],"gameUrl":"https://lichess.org/OuFIayw7#70","openingFamily":"","openingVariation":"","__v":0},{"theme":"","_id":"65e8c2a3a5e6cd0e9bcb2b40","uid":"hI44k","fen":"r1k5/ppp5/8/4R1b1/8/n1P5/PP3PPP/Kq2R3 w - - 7 32","moves":"e1b1 a3c2","rating":1028,"ratingDeviation":93,"randomNumberQuery":2634,"popularity":71,"nbPlays":447,"themes":["endgame","mate","mateIn1","oneMove","smotheredMate"],"gameUrl":"https://lichess.org/i2NkYHxQ#62","openingFamily":"","openingVariation":"","__v":0},{"theme":"","_id":"65e8c2c7a5e6cd0e9bcbaa6c","uid":"hYl6H","fen":"4r1Qk/pp4pp/1q5N/2b5/5P2/1P5P/P1Pr2P1/R4R1K b - - 8 24","moves":"e8g8 h6f7","rating":1032,"ratingDeviation":84,"randomNumberQuery":3682,"popularity":71,"nbPlays":91,"themes":["mate","mateIn1","middlegame","oneMove","smotheredMate"],"gameUrl":"https://lichess.org/LvDitQlW/black#47","openingFamily":"","openingVariation":"","__v":0},{"theme":"","_id":"65e8c2cba5e6cd0e9bcbb71e","uid":"haQ0N","fen":"r1bqk1nr/pppp1ppp/8/2b1p3/2PnP3/2N3P1/PP1P1P1P/R1BQKBNR w KQkq - 3 5","moves":"g1e2 d4f3","rating":1033,"ratingDeviation":86,"randomNumberQuery":7878,"popularity":91,"nbPlays":1035,"themes":["mate","mateIn1","oneMove","opening","smotheredMate"],"gameUrl":"https://lichess.org/amACt1xr#8","openingFamily":"","openingVariation":"","__v":0},{"theme":"","_id":"65e8c2cca5e6cd0e9bcbb97a","uid":"haisa","fen":"2rqkr2/1p1nb3/p3Nn2/7b/8/1Q5P/PP4P1/RNB2RK1 b - - 2 20","moves":"h5f7 e6g7","rating":1023,"ratingDeviation":89,"randomNumberQuery":8013,"popularity":88,"nbPlays":840,"themes":["mate","mateIn1","oneMove","opening","smotheredMate"],"gameUrl":"https://lichess.org/7LZxeSUr/black#39","openingFamily":"","openingVariation":"","__v":0},{"theme":"","_id":"65e8c320a5e6cd0e9bcce004","uid":"iCf0z","fen":"4r1Qk/ppp3pp/1bn3nN/8/3P4/2P3B1/PP2q1PP/R4R1K b - - 7 22","moves":"e8g8 h6f7","rating":1025,"ratingDeviation":89,"randomNumberQuery":7487,"popularity":89,"nbPlays":208,"themes":["mate","mateIn1","middlegame","oneMove","smotheredMate"],"gameUrl":"https://lichess.org/BPRvY1X0/black#43","openingFamily":"","openingVariation":"","__v":0},{"theme":"","_id":"65e8c33ca5e6cd0e9bcd452c","uid":"iQ3vB","fen":"6k1/5Qpp/5n2/3p2N1/3P4/8/2q2PPP/1q2R1K1 b - - 2 33","moves":"g8h8 f7f8 f6g8 g5f7","rating":1025,"ratingDeviation":78,"randomNumberQuery":5431,"popularity":89,"nbPlays":247,"themes":["endgame","mate","mateIn2","short","smotheredMate"],"gameUrl":"https://lichess.org/bhUcYe6Y/black#65","openingFamily":"","openingVariation":"","__v":0},{"theme":"","_id":"65e8c346a5e6cd0e9bcd6612","uid":"iUNZG","fen":"2rqkb1r/pp1nnppp/4p3/1N1pPb2/3P4/5N2/PP2BPPP/R1BQ1RK1 b k - 4 10","moves":"a7a6 b5d6","rating":1032,"ratingDeviation":193,"randomNumberQuery":1387,"popularity":54,"nbPlays":18,"themes":["mate","mateIn1","oneMove","opening","smotheredMate"],"gameUrl":"https://lichess.org/TBcrt4NP/black#19","openingFamily":"Caro-Kann_Defense","openingVariation":"Caro-Kann_Defense_Advance_Variation","__v":0},{"theme":"","_id":"65e8c390a5e6cd0e9bce6c30","uid":"j2cBR","fen":"r1bqkb1r/p3nppp/1p2p3/1Npp4/Q3P3/5N2/PPPP1PPP/R1B1K2R b KQkq - 1 9","moves":"c8d7 b5d6","rating":1032,"ratingDeviation":131,"randomNumberQuery":5300,"popularity":69,"nbPlays":112,"themes":["mate","mateIn1","oneMove","opening","smotheredMate"],"gameUrl":"https://lichess.org/00Rq927M/black#17","openingFamily":"","openingVariation":"","__v":0},{"theme":"","_id":"65e8c3a1a5e6cd0e9bceab12","uid":"jApyG","fen":"r5k1/1b2rppp/p3p3/1pp5/5P2/P1P3Nn/BP4PP/2Q1RRqK w - - 5 23","moves":"f1g1 h3f2","rating":1023,"ratingDeviation":92,"randomNumberQuery":7124,"popularity":100,"nbPlays":40,"themes":["mate","mateIn1","middlegame","oneMove","smotheredMate"],"gameUrl":"https://lichess.org/eX2rL0Pa#44","openingFamily":"","openingVariation":"","__v":0},{"theme":"","_id":"65e8c3bca5e6cd0e9bcf0900","uid":"jMzUD","fen":"1n3rQk/p3b1pp/1p6/2q1N3/2B5/8/PP3PPP/3R2K1 b - - 4 21","moves":"f8g8 e5f7","rating":1039,"ratingDeviation":82,"randomNumberQuery":7902,"popularity":53,"nbPlays":66,"themes":["mate","mateIn1","middlegame","oneMove","smotheredMate"],"gameUrl":"https://lichess.org/ZaT3AWBM/black#41","openingFamily":"","openingVariation":"","__v":0},{"theme":"","_id":"65e8c3caa5e6cd0e9bcf3b9a","uid":"jTgYW","fen":"1k1r1b1r/ppp3pp/2n1p3/4P1B1/Q3P3/2P2N1n/PP4PP/RN3RqK w - - 9 16","moves":"f1g1 h3f2","rating":1022,"ratingDeviation":79,"randomNumberQuery":3200,"popularity":50,"nbPlays":87,"themes":["mate","mateIn1","middlegame","oneMove","smotheredMate"],"gameUrl":"https://lichess.org/X8Bwd7gS#30","openingFamily":"Kings_Gambit","openingVariation":"Kings_Gambit_Other_variations","__v":0},{"theme":"","_id":"65e8c3e2a5e6cd0e9bcf8943","uid":"jdn31","fen":"6k1/pp6/4p2Q/5p2/6p1/PPr4n/6PP/4R1qK w - - 6 42","moves":"e1g1 h3f2","rating":1039,"ratingDeviation":107,"randomNumberQuery":5245,"popularity":72,"nbPlays":203,"themes":["endgame","mate","mateIn1","oneMove","smotheredMate"],"gameUrl":"https://lichess.org/Lww9xkcl#82","openingFamily":"","openingVariation":"","__v":0},{"theme":"","_id":"65e8c42aa5e6cd0e9bd08a0b","uid":"kBTyP","fen":"r2qkbnr/pp1n1ppp/2b5/1Np1p3/P2pP3/1P1P1NP1/2P2P1P/R1BQKB1R b KQkq - 0 8","moves":"g8e7 b5d6","rating":1029,"ratingDeviation":76,"randomNumberQuery":6493,"popularity":89,"nbPlays":433,"themes":["mate","mateIn1","oneMove","opening","smotheredMate"],"gameUrl":"https://lichess.org/Rky74Tuk/black#15","openingFamily":"Van_Geet_Opening","openingVariation":"Van_Geet_Opening_Other_variations","__v":0},{"theme":"","_id":"65e8c43ba5e6cd0e9bd0c39d","uid":"kIuC1","fen":"r4rk1/pp4pp/2n1R3/3Q4/8/5N1n/PPP3PP/RN4qK w - - 6 18","moves":"f3g1 h3f2","rating":1026,"ratingDeviation":75,"randomNumberQuery":4397,"popularity":75,"nbPlays":252,"themes":["mate","mateIn1","middlegame","oneMove","smotheredMate"],"gameUrl":"https://lichess.org/a8vYsAVX#34","openingFamily":"French_Defense","openingVariation":"French_Defense_Knight_Variation","__v":0},{"theme":"","_id":"65e8c447a5e6cd0e9bd0ec93","uid":"kOE7m","fen":"2kr1b1r/ppp3pp/8/3p4/1n1NNPP1/4P2P/qPPBQ3/2KR3R w - - 0 17","moves":"e4c3 a2a1 c3b1 b4a2","rating":1023,"ratingDeviation":83,"randomNumberQuery":1879,"popularity":91,"nbPlays":459,"themes":["mate","mateIn2","middlegame","queensideAttack","short","smotheredMate"],"gameUrl":"https://lichess.org/FMDJgczP#32","openingFamily":"Englund_Gambit","openingVariation":"Englund_Gambit_Other_variations","__v":0},{"theme":"","_id":"65e8c44fa5e6cd0e9bd10aa9","uid":"kS9yW","fen":"r1bq1rkn/pp1pnppp/2p5/4PP2/1bBPN1Q1/8/PPP3PP/R1B2RK1 b - - 1 12","moves":"d7d5 e4f6","rating":1037,"ratingDeviation":84,"randomNumberQuery":5746,"popularity":90,"nbPlays":775,"themes":["mate","mateIn1","oneMove","opening","pin","smotheredMate"],"gameUrl":"https://lichess.org/ftwH5Yyx/black#23","openingFamily":"Four_Knights_Game","openingVariation":"Four_Knights_Game_Halloween_Gambit","__v":0},{"theme":"","_id":"65e8c459a5e6cd0e9bd12e51","uid":"kWswq","fen":"5r1k/1p2b1pp/p1n1Q3/8/8/2N4n/PPPB2PP/R5qK w - - 6 23","moves":"a1g1 h3f2","rating":1036,"ratingDeviation":76,"randomNumberQuery":3391,"popularity":87,"nbPlays":166,"themes":["mate","mateIn1","middlegame","oneMove","smotheredMate"],"gameUrl":"https://lichess.org/0NkNAd9u#44","openingFamily":"","openingVariation":"","__v":0},{"theme":"","_id":"65e8c45aa5e6cd0e9bd13153","uid":"kXKkm","fen":"r4k1r/pp4bp/4Q1p1/4P3/8/P6n/1P4PP/RN2R1qK w - - 7 23","moves":"e1g1 h3f2","rating":1026,"ratingDeviation":100,"randomNumberQuery":3352,"popularity":57,"nbPlays":103,"themes":["mate","mateIn1","middlegame","oneMove","smotheredMate"],"gameUrl":"https://lichess.org/c7hjIcAT#44","openingFamily":"","openingVariation":"","__v":0},{"theme":"","_id":"65e8c47aa5e6cd0e9bd19cbf","uid":"klKE5","fen":"kQ3r2/pp2b1p1/Nn2Bn1p/q2p4/3Pp1P1/4B2P/PPP5/2KR3R b - - 9 26","moves":"f8b8 a6c7","rating":1030,"ratingDeviation":114,"randomNumberQuery":3421,"popularity":50,"nbPlays":43,"themes":["mate","mateIn1","middlegame","oneMove","smotheredMate"],"gameUrl":"https://lichess.org/TcQN1pkw/black#51","openingFamily":"","openingVariation":"","__v":0},{"theme":"","_id":"65e8c482a5e6cd0e9bd1ba05","uid":"kpBFt","fen":"1nkr3r/pppqbpp1/4p3/1N1pPn2/3P3p/P2QBN1P/2P2PP1/1R3RK1 b - - 4 15","moves":"a7a6 b5a7","rating":1036,"ratingDeviation":88,"randomNumberQuery":6440,"popularity":73,"nbPlays":176,"themes":["mate","mateIn1","middlegame","oneMove","smotheredMate"],"gameUrl":"https://lichess.org/1VFduqrM/black#29","openingFamily":"Nimzowitsch_Defense","openingVariation":"Nimzowitsch_Defense_Scandinavian_Variation","__v":0},{"theme":"","_id":"65e8c4bfa5e6cd0e9bd28943","uid":"lGAbW","fen":"r5rk/p5bp/2p1b2p/2qpN3/6Q1/5N1P/P1P2PP1/3R1RK1 b - - 2 23","moves":"e6g4 e5f7","rating":1038,"ratingDeviation":98,"randomNumberQuery":7419,"popularity":81,"nbPlays":270,"themes":["mate","mateIn1","middlegame","oneMove","smotheredMate"],"gameUrl":"https://lichess.org/ykNhOeTd/black#45","openingFamily":"","openingVariation":"","__v":0},{"theme":"","_id":"65e8c4ffa5e6cd0e9bd36b3b","uid":"ljabG","fen":"3Qb1k1/p4ppp/2p5/8/B2q4/1P2r3/PBP3PP/R2n3K w - - 3 22","moves":"b2d4 e3e1 d4g1 d1f2","rating":1026,"ratingDeviation":76,"randomNumberQuery":4545,"popularity":95,"nbPlays":1913,"themes":["mate","mateIn2","middlegame","pin","short","smotheredMate"],"gameUrl":"https://lichess.org/3DECoHIO#42","openingFamily":"","openingVariation":"","__v":0},{"theme":"","_id":"65e8c506a5e6cd0e9bd383ab","uid":"lmo6s","fen":"3qkbnr/3n1ppp/4p3/rN2P3/P2P4/2p2N2/4QPPP/1RR3K1 b k - 3 19","moves":"g8e7 b5d6","rating":1024,"ratingDeviation":93,"randomNumberQuery":5899,"popularity":90,"nbPlays":260,"themes":["mate","mateIn1","middlegame","oneMove","smotheredMate"],"gameUrl":"https://lichess.org/e1iGez5L/black#37","openingFamily":"Caro-Kann_Defense","openingVariation":"Caro-Kann_Defense_Advance_Variation","__v":0},{"theme":"","_id":"65e8c524a5e6cd0e9bd3ef41","uid":"m0iFt","fen":"r2qkb1r/3bnppp/p3p3/2p1P3/2PpN3/4B3/PPQ1BPPP/3RK2R b Kkq - 1 14","moves":"d4e3 e4d6","rating":1023,"ratingDeviation":75,"randomNumberQuery":7549,"popularity":96,"nbPlays":1103,"themes":["mate","mateIn1","middlegame","oneMove","smotheredMate"],"gameUrl":"https://lichess.org/j1KezYID/black#27","openingFamily":"Sicilian_Defense","openingVariation":"Sicilian_Defense_Kan_Variation","__v":0},{"theme":"","_id":"65e8c55da5e6cd0e9bd4b9d9","uid":"mRPtS","fen":"4r1k1/1B3ppp/r3b3/P1b5/5Pn1/P1Bp4/6PP/RN1Q1RqK w - - 10 27","moves":"f1g1 g4f2","rating":1028,"ratingDeviation":369,"randomNumberQuery":3308,"popularity":-48,"nbPlays":13,"themes":["mate","mateIn1","middlegame","oneMove","smotheredMate"],"gameUrl":"https://lichess.org/9I2wjAaM#52","openingFamily":"","openingVariation":"","__v":0},{"theme":"","_id":"65e8c561a5e6cd0e9bd4c74b","uid":"mTBou","fen":"r2qkb1r/1p3ppp/p2p1n2/2pPp3/3nP3/P2P4/1P1BNPPP/R2QKB1R w KQkq - 1 10","moves":"g2g3 d4f3","rating":1021,"ratingDeviation":90,"randomNumberQuery":4413,"popularity":85,"nbPlays":414,"themes":["mate","mateIn1","middlegame","oneMove","smotheredMate"],"gameUrl":"https://lichess.org/Kn6nbsow#18","openingFamily":"English_Opening","openingVariation":"English_Opening_Anglo-Indian_Defense","__v":0},{"theme":"","_id":"65e8c577a5e6cd0e9bd512a4","uid":"md3hh","fen":"r2qkb1r/pb1nnppp/1p2p3/2p5/3PN3/P1PB1N2/1P3PPP/R1BQ1RK1 b kq - 0 9","moves":"c5d4 e4d6","rating":1022,"ratingDeviation":84,"randomNumberQuery":7267,"popularity":92,"nbPlays":331,"themes":["mate","mateIn1","oneMove","opening","smotheredMate"],"gameUrl":"https://lichess.org/40P43hjh/black#17","openingFamily":"French_Defense","openingVariation":"French_Defense_Tarrasch_Variation","__v":0},{"theme":"","_id":"65e8c57aa5e6cd0e9bd51d7e","uid":"meTTP","fen":"r4rk1/p2n2pp/4p3/1p1P4/2p5/P1P4n/1PQN2PP/R1B1R1qK w - - 5 23","moves":"e1g1 h3f2","rating":1029,"ratingDeviation":88,"randomNumberQuery":2805,"popularity":78,"nbPlays":235,"themes":["mate","mateIn1","middlegame","oneMove","smotheredMate"],"gameUrl":"https://lichess.org/ySvfI9KQ#44","openingFamily":"","openingVariation":"","__v":0},{"theme":"","_id":"65e8c5b9a5e6cd0e9bd5f00b","uid":"n64Bn","fen":"r5k1/1p3pp1/4p2p/1N1p4/8/2P4n/6NP/1Q3RqK w - - 6 32","moves":"f1g1 h3f2","rating":1021,"ratingDeviation":88,"randomNumberQuery":1964,"popularity":77,"nbPlays":143,"themes":["endgame","mate","mateIn1","oneMove","smotheredMate"],"gameUrl":"https://lichess.org/YCdwOdho#62","openingFamily":"","openingVariation":"","__v":0},{"theme":"","_id":"65e8c5baa5e6cd0e9bd5f23f","uid":"n6MCa","fen":"7k/6p1/2N1Qp1p/rpPp4/3P4/7n/6PP/5RqK w - - 9 37","moves":"f1g1 h3f2","rating":1029,"ratingDeviation":75,"randomNumberQuery":3529,"popularity":100,"nbPlays":136,"themes":["endgame","mate","mateIn1","oneMove","smotheredMate"],"gameUrl":"https://lichess.org/mj4DND4a#72","openingFamily":"","openingVariation":"","__v":0},{"theme":"","_id":"65e8c611a5e6cd0e9bd70ef5","uid":"nhIwl","fen":"4Qbk1/p4p1p/3p2p1/8/3P4/2Pn1NB1/Pq4PP/5NK1 w - - 1 28","moves":"g3d6 b2f2 g1h1 f2f1 f3g1 d3f2","rating":1020,"ratingDeviation":77,"randomNumberQuery":7493,"popularity":97,"nbPlays":1665,"themes":["deflection","long","mate","mateIn3","middlegame","smotheredMate"],"gameUrl":"https://lichess.org/Oop9d8nZ#54","openingFamily":"","openingVariation":"","__v":0},{"theme":"","_id":"65e8c639a5e6cd0e9bd799f3","uid":"nzZ0Q","fen":"r1bqkb1r/ppp2ppp/5n2/4p3/1nPp4/1P2P3/PB1PNPPP/R2QKBNR w KQkq - 2 7","moves":"a2a3 b4d3","rating":1020,"ratingDeviation":92,"randomNumberQuery":9890,"popularity":90,"nbPlays":699,"themes":["mate","mateIn1","oneMove","opening","smotheredMate"],"gameUrl":"https://lichess.org/qEOjXzau#12","openingFamily":"","openingVariation":"","__v":0},{"theme":"","_id":"65e8c63ba5e6cd0e9bd79f5f","uid":"o0IR9","fen":"r1b2rQk/pppp2pp/1b5N/8/3Pp2q/P1N5/1P3PPP/R1B1R1K1 b - - 9 17","moves":"f8g8 h6f7","rating":1036,"ratingDeviation":80,"randomNumberQuery":1955,"popularity":77,"nbPlays":254,"themes":["mate","mateIn1","middlegame","oneMove","smotheredMate"],"gameUrl":"https://lichess.org/IJRcBbLn/black#33","openingFamily":"","openingVariation":"","__v":0},{"theme":"","_id":"65e8c65ca5e6cd0e9bd81183","uid":"oFA9e","fen":"3qkb1r/2pnnpp1/rp1pp2p/1N6/P2PP3/4B3/2P2PPP/R2QK1NR b KQk - 1 10","moves":"c7c6 b5d6","rating":1039,"ratingDeviation":75,"randomNumberQuery":6875,"popularity":71,"nbPlays":133,"themes":["mate","mateIn1","oneMove","opening","smotheredMate"],"gameUrl":"https://lichess.org/oZW0ianL/black#19","openingFamily":"Rat_Defense","openingVariation":"Rat_Defense_Small_Center_Defense","__v":0},{"theme":"","_id":"65e8c661a5e6cd0e9bd82219","uid":"oHMV9","fen":"r2qkbnr/pp1n1p2/2p4p/4pNpP/3pP3/3P1B2/PPP2PP1/R1BQK2R b KQkq - 1 11","moves":"g8e7 f5d6","rating":1028,"ratingDeviation":156,"randomNumberQuery":478,"popularity":65,"nbPlays":39,"themes":["mate","mateIn1","oneMove","opening","smotheredMate"],"gameUrl":"https://lichess.org/nRFDeQ8g/black#21","openingFamily":"Caro-Kann_Defense","openingVariation":"Caro-Kann_Defense_Two_Knights_Attack","__v":0},{"theme":"","_id":"65e8c676a5e6cd0e9bd862f7","uid":"oPr2L","fen":"r2qkb1r/pp1bpppp/5n2/1Np5/2P1p3/5N1P/PP1P1PP1/R1BQR1K1 b kq - 0 11","moves":"e4f3 b5d6","rating":1028,"ratingDeviation":86,"randomNumberQuery":3453,"popularity":88,"nbPlays":5769,"themes":["mate","mateIn1","oneMove","opening","pin","smotheredMate"],"gameUrl":"https://lichess.org/7hSrQL5x/black#21","openingFamily":"Sicilian_Defense","openingVariation":"Sicilian_Defense_Modern_Variations","__v":0},{"theme":"","_id":"65e8c6caa5e6cd0e9bd97887","uid":"p0AFJ","fen":"rnbqkb1r/p4ppp/1p6/2p1p3/4Pn2/3P3P/PP1N1PP1/R1BQKBNR w KQkq - 1 8","moves":"g1e2 f4d3","rating":1026,"ratingDeviation":88,"randomNumberQuery":1782,"popularity":90,"nbPlays":335,"themes":["mate","mateIn1","oneMove","opening","smotheredMate"],"gameUrl":"https://lichess.org/W7x8FEJ8#14","openingFamily":"","openingVariation":"","__v":0},{"theme":"","_id":"65e8c706a5e6cd0e9bda4469","uid":"pQx0m","fen":"r1bqkbnr/pp1n1ppp/2p1p3/8/3PNB2/5N2/PPP2PPP/R2QKB1R b KQkq - 0 6","moves":"g8e7 e4d6","rating":1028,"ratingDeviation":80,"randomNumberQuery":3048,"popularity":67,"nbPlays":77,"themes":["mate","mateIn1","oneMove","opening","smotheredMate"],"gameUrl":"https://lichess.org/7vWiqz8X/black#11","openingFamily":"French_Defense","openingVariation":"French_Defense_Two_Knights_Variation","__v":0},{"theme":"","_id":"65e8c71ca5e6cd0e9bda866f","uid":"pZY0t","fen":"rn2r1k1/p4pp1/1p5p/3p4/3P2n1/BQPBP2R/P5PP/5RqK w - - 2 21","moves":"f1g1 g4f2","rating":1032,"ratingDeviation":120,"randomNumberQuery":7730,"popularity":100,"nbPlays":32,"themes":["mate","mateIn1","middlegame","oneMove","smotheredMate"],"gameUrl":"https://lichess.org/Vz3DD2M3#40","openingFamily":"","openingVariation":"","__v":0},{"theme":"","_id":"65e8c754a5e6cd0e9bdb4d39","uid":"pziQl","fen":"r1br2Qk/2qpn1bp/ppnR2pN/4p3/P3P3/2N1B3/1P3PPP/3R2K1 b - - 9 20","moves":"d8g8 h6f7","rating":1022,"ratingDeviation":91,"randomNumberQuery":3714,"popularity":60,"nbPlays":66,"themes":["mate","mateIn1","middlegame","oneMove","smotheredMate"],"gameUrl":"https://lichess.org/ZNE9tdWO/black#39","openingFamily":"","openingVariation":"","__v":0},{"theme":"","_id":"65e8c760a5e6cd0e9bdb75ab","uid":"q58vl","fen":"2r3Qk/p2p2bp/qp4pN/5p2/8/4B1P1/PP3P1P/5RK1 b - - 5 26","moves":"c8g8 h6f7","rating":1039,"ratingDeviation":89,"randomNumberQuery":1582,"popularity":76,"nbPlays":203,"themes":["endgame","mate","mateIn1","oneMove","smotheredMate"],"gameUrl":"https://lichess.org/YZ99AqxW/black#51","openingFamily":"","openingVariation":"","__v":0},{"theme":"","_id":"65e8c795a5e6cd0e9bdc35ef","uid":"qULnp","fen":"r1bkr3/1pppnRpp/p7/4n3/3NP3/2N1P3/PPPQB1qP/2KR4 b - - 0 14","moves":"e5f7 d4e6","rating":1028,"ratingDeviation":77,"randomNumberQuery":8219,"popularity":92,"nbPlays":732,"themes":["mate","mateIn1","middlegame","oneMove","pin","smotheredMate"],"gameUrl":"https://lichess.org/27FAbLmV/black#27","openingFamily":"Scotch_Game","openingVariation":"Scotch_Game_Blumenfeld_Attack","__v":0},{"theme":"","_id":"65e8c7b8a5e6cd0e9bdcb1c5","uid":"qkRRJ","fen":"r2qkb1r/1b1pnpp1/p1n1p2p/1p1N4/4P2B/1B3N2/PP3PPP/R2Q1RK1 b kq - 1 11","moves":"g7g5 d5f6","rating":1036,"ratingDeviation":89,"randomNumberQuery":1023,"popularity":85,"nbPlays":488,"themes":["master","mate","mateIn1","middlegame","oneMove","smotheredMate"],"gameUrl":"https://lichess.org/F7fC9s60/black#21","openingFamily":"Sicilian_Defense","openingVariation":"Sicilian_Defense_Smith-Morra_Gambit_Accepted","__v":0},{"theme":"","_id":"65e8c7e1a5e6cd0e9bdd444b","uid":"r3e0A","fen":"4r1k1/pp3ppp/2n5/1N1Q3b/B7/B1P2P1n/P1P3PP/R5qK w - - 5 21","moves":"a1g1 h3f2","rating":1029,"ratingDeviation":75,"randomNumberQuery":9144,"popularity":100,"nbPlays":213,"themes":["mate","mateIn1","middlegame","oneMove","smotheredMate"],"gameUrl":"https://lichess.org/AlxyeZXS#40","openingFamily":"","openingVariation":"","__v":0},{"theme":"","_id":"65e8c801a5e6cd0e9bddb6f1","uid":"rISWV","fen":"r1b1kbnr/ppp1qp1p/3p4/4n1p1/8/2P3BP/PP2PPP1/RN1QKBNR w KQkq - 0 7","moves":"b1d2 e5d3","rating":1033,"ratingDeviation":89,"randomNumberQuery":7621,"popularity":90,"nbPlays":197,"themes":["mate","mateIn1","oneMove","opening","pin","smotheredMate"],"gameUrl":"https://lichess.org/wtb5sOqu#12","openingFamily":"","openingVariation":"","__v":0},{"theme":"","_id":"65e8c81ba5e6cd0e9bde112b","uid":"rU95N","fen":"r2qkb1r/1b1pnpp1/p3p2p/1p1N4/4P2B/1Q3N2/PP3PPP/R3R1K1 b kq - 1 13","moves":"g7g5 d5f6","rating":1030,"ratingDeviation":102,"randomNumberQuery":4710,"popularity":68,"nbPlays":85,"themes":["mate","mateIn1","middlegame","oneMove","smotheredMate"],"gameUrl":"https://lichess.org/sNmmISy0/black#25","openingFamily":"Sicilian_Defense","openingVariation":"Sicilian_Defense_Smith-Morra_Gambit_Accepted","__v":0},{"theme":"","_id":"65e8c878a5e6cd0e9bdf5b01","uid":"sB7GH","fen":"kQr4r/pp4pp/N7/8/8/2P1PK2/Pq4PP/R2R4 b - - 6 29","moves":"c8b8 a6c7","rating":1022,"ratingDeviation":91,"randomNumberQuery":553,"popularity":77,"nbPlays":165,"themes":["endgame","mate","mateIn1","oneMove","smotheredMate"],"gameUrl":"https://lichess.org/wp3N0QXX/black#57","openingFamily":"","openingVariation":"","__v":0},{"theme":"","_id":"65e8c879a5e6cd0e9bdf5d43","uid":"sBQEd","fen":"7r/p4pk1/2p3b1/1p2q3/4N3/3rnP2/PP5R/KN2Q2R w - - 8 29","moves":"h2h8 e3c2","rating":1032,"ratingDeviation":92,"randomNumberQuery":5777,"popularity":73,"nbPlays":254,"themes":["mate","mateIn1","middlegame","oneMove","smotheredMate"],"gameUrl":"https://lichess.org/fiTohmbo#56","openingFamily":"","openingVariation":"","__v":0},{"theme":"","_id":"65e8c887a5e6cd0e9bdf8df3","uid":"sHn1R","fen":"r5Qk/pb4pp/1p5N/8/3q1P2/1P6/P1Pp2PP/5R1K b - - 7 29","moves":"a8g8 h6f7","rating":1033,"ratingDeviation":110,"randomNumberQuery":8470,"popularity":68,"nbPlays":135,"themes":["endgame","mate","mateIn1","oneMove","smotheredMate"],"gameUrl":"https://lichess.org/BZWrUxlv/black#57","openingFamily":"","openingVariation":"","__v":0},{"theme":"","_id":"65e8c8b5a5e6cd0e9be030bc","uid":"scxYj","fen":"4r1Qk/pp1RP1pp/1b3p1N/8/8/7P/Pqr2PP1/5RK1 b - - 4 28","moves":"e8g8 h6f7","rating":1036,"ratingDeviation":75,"randomNumberQuery":4908,"popularity":100,"nbPlays":199,"themes":["mate","mateIn1","middlegame","oneMove","smotheredMate"],"gameUrl":"https://lichess.org/A8l35r4C/black#55","openingFamily":"","openingVariation":"","__v":0},{"theme":"","_id":"65e8c8e2a5e6cd0e9be0cea0","uid":"sxKif","fen":"r2r2k1/pp4pp/4b3/4Qp2/1b6/n1N2PN1/PP1B2PP/Kq1R3R w - - 7 21","moves":"c3b1 a3c2","rating":1038,"ratingDeviation":89,"randomNumberQuery":94,"popularity":75,"nbPlays":321,"themes":["mate","mateIn1","middlegame","oneMove","smotheredMate"],"gameUrl":"https://lichess.org/fhRibdi4#40","openingFamily":"","openingVariation":"","__v":0},{"theme":"","_id":"65e8c8e6a5e6cd0e9be0db5e","uid":"sz2Lw","fen":"r4rQk/6pp/p1p4N/2Pp4/P2qp3/7P/5RP1/R5K1 b - - 3 38","moves":"f8g8 h6f7","rating":1027,"ratingDeviation":95,"randomNumberQuery":9742,"popularity":76,"nbPlays":482,"themes":["endgame","mate","mateIn1","oneMove","smotheredMate"],"gameUrl":"https://lichess.org/rpJtAWGT/black#75","openingFamily":"","openingVariation":"","__v":0},{"theme":"","_id":"65e8c96ea5e6cd0e9be2ac83","uid":"txY2Z","fen":"r4rQk/2p3pp/p1Pb2pN/1p6/5P1B/P3P2P/3n2P1/1R3RK1 b - - 6 36","moves":"f8g8 h6f7","rating":1020,"ratingDeviation":109,"randomNumberQuery":2944,"popularity":83,"nbPlays":156,"themes":["mate","mateIn1","middlegame","oneMove","smotheredMate"],"gameUrl":"https://lichess.org/o6nmGYB8/black#71","openingFamily":"","openingVariation":"","__v":0},{"theme":"","_id":"65e8c96fa5e6cd0e9be2af0b","uid":"txs6s","fen":"5rk1/rP3Bpp/2n2n2/2P2bN1/3pP2q/NQ3P2/P5P1/R1B1bK2 b - - 0 24","moves":"f8f7 b3f7 g8h8 f7f8 f6g8 g5f7","rating":1027,"ratingDeviation":77,"randomNumberQuery":1015,"popularity":96,"nbPlays":5790,"themes":["kingsideAttack","long","mate","mateIn3","middlegame","smotheredMate"],"gameUrl":"https://lichess.org/zktIr7zY/black#47","openingFamily":"","openingVariation":"","__v":0},{"theme":"","_id":"65e8c98ca5e6cd0e9be316c7","uid":"uBQnl","fen":"rnbq1rQk/pp1p2pp/2p5/4N1b1/2B1N3/8/PPP2PPP/R3K2R b KQ - 1 11","moves":"f8g8 e5f7","rating":1036,"ratingDeviation":98,"randomNumberQuery":7997,"popularity":83,"nbPlays":128,"themes":["mate","mateIn1","middlegame","oneMove","smotheredMate"],"gameUrl":"https://lichess.org/xnMmhmjp/black#21","openingFamily":"Duras_Gambit","openingVariation":"Duras_Gambit_Other_variations","__v":0},{"theme":"","_id":"65e8c992a5e6cd0e9be32aed","uid":"uE2LY","fen":"3r1rk1/pp1n1pbp/6p1/4p1B1/2N1P3/2Pp2Nn/PP4PP/R1QR2qK w - - 7 20","moves":"d1g1 h3f2","rating":1039,"ratingDeviation":96,"randomNumberQuery":338,"popularity":100,"nbPlays":92,"themes":["mate","mateIn1","middlegame","oneMove","smotheredMate"],"gameUrl":"https://lichess.org/N9gXBsD2#38","openingFamily":"","openingVariation":"","__v":0},{"theme":"","_id":"65e8c9ada5e6cd0e9be37e5b","uid":"uOt9e","fen":"r2qkb1r/3pnppp/p3p3/1p6/3PN3/PB3N2/1P3PPP/R1nQ1RK1 b kq - 0 13","moves":"c1b3 e4d6","rating":1028,"ratingDeviation":77,"randomNumberQuery":669,"popularity":99,"nbPlays":1330,"themes":["mate","mateIn1","oneMove","opening","smotheredMate"],"gameUrl":"https://lichess.org/KHi5eLo3/black#25","openingFamily":"Sicilian_Defense","openingVariation":"Sicilian_Defense_Nyezhmetdinov-Rossolimo_Attack","__v":0},{"theme":"","_id":"65e8c9e7a5e6cd0e9be4412d","uid":"uocko","fen":"2r2r1k/ppp3b1/7p/1P2n1p1/5p2/BQP2N1n/P5PP/RN1R2qK w - - 9 21","moves":"d1g1 h3f2","rating":1035,"ratingDeviation":89,"randomNumberQuery":3136,"popularity":54,"nbPlays":175,"themes":["master","mate","mateIn1","middlegame","oneMove","smotheredMate"],"gameUrl":"https://lichess.org/26FWK23J#40","openingFamily":"","openingVariation":"","__v":0},{"theme":"","_id":"65e8c9eca5e6cd0e9be4531d","uid":"ur5ns","fen":"r1b2rk1/pp3p1p/4p1p1/4P3/2p5/2P2NPn/PP4BP/R1Q1R1qK w - - 12 23","moves":"e1g1 h3f2","rating":1021,"ratingDeviation":95,"randomNumberQuery":9998,"popularity":79,"nbPlays":265,"themes":["kingsideAttack","mate","mateIn1","middlegame","oneMove","smotheredMate"],"gameUrl":"https://lichess.org/ZtUgAemr#44","openingFamily":"","openingVariation":"","__v":0},{"theme":"","_id":"65e8ca2ea5e6cd0e9be538a1","uid":"vKv7W","fen":"1nkr1b1r/pbp1qpp1/1p1p3p/1N1P4/3B4/2P2N2/PP3PPP/R2Q1RK1 b - - 2 13","moves":"e7d7 b5a7","rating":1034,"ratingDeviation":99,"randomNumberQuery":3559,"popularity":75,"nbPlays":53,"themes":["mate","mateIn1","oneMove","opening","queensideAttack","smotheredMate"],"gameUrl":"https://lichess.org/s11b0e6t/black#25","openingFamily":"Bishops_Opening","openingVariation":"Bishops_Opening_Other_variations","__v":0},{"theme":"","_id":"65e8ca4aa5e6cd0e9be59389","uid":"vWshj","fen":"R3Q3/5pkp/4p1p1/8/8/5B1n/1r1r2PP/5RqK w - - 22 39","moves":"f1g1 h3f2","rating":1024,"ratingDeviation":82,"randomNumberQuery":2640,"popularity":33,"nbPlays":73,"themes":["mate","mateIn1","middlegame","oneMove","smotheredMate"],"gameUrl":"https://lichess.org/F3zLCatF#76","openingFamily":"","openingVariation":"","__v":0},{"theme":"","_id":"65e8ca67a5e6cd0e9be5f62b","uid":"vjpsz","fen":"5rQk/3pR1pp/7N/2p5/8/P7/1r1q1PPP/R5K1 b - - 4 22","moves":"f8g8 h6f7","rating":1037,"ratingDeviation":96,"randomNumberQuery":1060,"popularity":82,"nbPlays":31,"themes":["endgame","mate","mateIn1","oneMove","smotheredMate"],"gameUrl":"https://lichess.org/fkgcWU4j/black#43","openingFamily":"","openingVariation":"","__v":0},{"theme":"","_id":"65e8ca90a5e6cd0e9be67a4b","uid":"w1CId","fen":"2b2rk1/2p4p/1p1p4/3P3N/1QP2p2/2N4n/2B3PP/5RqK w - - 9 32","moves":"f1g1 h3f2","rating":1036,"ratingDeviation":187,"randomNumberQuery":4408,"popularity":60,"nbPlays":46,"themes":["mate","mateIn1","middlegame","oneMove","smotheredMate"],"gameUrl":"https://lichess.org/M1tGhktL#62","openingFamily":"","openingVariation":"","__v":0},{"theme":"","_id":"65e8caa8a5e6cd0e9be6cf5f","uid":"wCW0W","fen":"r3kb1Q/pp2p3/2b2pp1/3p4/1P3P2/7n/P1P3PP/RNB2RqK w q - 6 17","moves":"f1g1 h3f2","rating":1021,"ratingDeviation":105,"randomNumberQuery":92,"popularity":82,"nbPlays":143,"themes":["mate","mateIn1","middlegame","oneMove","smotheredMate"],"gameUrl":"https://lichess.org/ffHDiHGW#32","openingFamily":"Caro-Kann_Defense","openingVariation":"Caro-Kann_Defense_Other_variations","__v":0},{"theme":"","_id":"65e8caa9a5e6cd0e9be6d3cf","uid":"wD4Cm","fen":"rn1qkbnr/pp2pppp/2p3b1/8/4N1P1/5N1P/PPPPQP2/R1B1KB1R b KQkq - 2 7","moves":"b8d7 e4d6","rating":1035,"ratingDeviation":85,"randomNumberQuery":2108,"popularity":91,"nbPlays":1902,"themes":["mate","mateIn1","oneMove","opening","pin","smotheredMate"],"gameUrl":"https://lichess.org/tpBLSAqP/black#13","openingFamily":"","openingVariation":"","__v":0},{"theme":"","_id":"65e8cae7a5e6cd0e9be7a949","uid":"wetdh","fen":"r1bqkb1r/pp2npp1/3p3p/1B1np3/4N3/5N2/PPP2PPP/R1BQ1RK1 b kq - 1 10","moves":"c8d7 e4d6","rating":1038,"ratingDeviation":77,"randomNumberQuery":2176,"popularity":95,"nbPlays":2863,"themes":["mate","mateIn1","oneMove","opening","smotheredMate"],"gameUrl":"https://lichess.org/nDGKtxvz/black#19","openingFamily":"Philidor_Defense","openingVariation":"Philidor_Defense_Other_variations","__v":0},{"theme":"","_id":"65e8cb2ca5e6cd0e9be89be1","uid":"xAhre","fen":"1r1Qkb1r/pp1npq1p/2p1N1p1/3p4/4nB2/3B4/PPP2PPP/R3R1K1 b k - 2 17","moves":"b8d8 e6c7","rating":1034,"ratingDeviation":87,"randomNumberQuery":2262,"popularity":90,"nbPlays":626,"themes":["mate","mateIn1","middlegame","oneMove","smotheredMate"],"gameUrl":"https://lichess.org/LnVBgkjA/black#33","openingFamily":"Caro-Kann_Defense","openingVariation":"Caro-Kann_Defense_Campomanes_Attack","__v":0},{"theme":"","_id":"65e8cb5ea5e6cd0e9be95007","uid":"xY910","fen":"4r1k1/1b3ppp/1p6/3p4/1Q1N4/P6n/4B1PP/5RqK w - - 6 29","moves":"f1g1 h3f2","rating":1021,"ratingDeviation":89,"randomNumberQuery":5219,"popularity":59,"nbPlays":176,"themes":["mate","mateIn1","middlegame","oneMove","smotheredMate"],"gameUrl":"https://lichess.org/O9vhhXs6#56","openingFamily":"","openingVariation":"","__v":0},{"theme":"","_id":"65e8cbb4a5e6cd0e9bea6fb2","uid":"y9nAl","fen":"r2q2k1/pppb1p1p/2n1p3/6P1/1bP2n2/1P6/PB1P1P1P/R2QKBNR w KQ - 0 13","moves":"g1e2 f4d3","rating":1036,"ratingDeviation":92,"randomNumberQuery":5208,"popularity":89,"nbPlays":425,"themes":["mate","mateIn1","middlegame","oneMove","smotheredMate"],"gameUrl":"https://lichess.org/HWP6Flhf#24","openingFamily":"French_Defense","openingVariation":"French_Defense_Horwitz_Attack","__v":0},{"theme":"","_id":"65e8cbc9a5e6cd0e9beab906","uid":"yJRGD","fen":"1rbqkb1r/p2pnppp/1p2p3/1Np5/2P5/4PBP1/PP1P1P1P/R1BQ1RK1 b k - 1 9","moves":"a7a6 b5d6","rating":1032,"ratingDeviation":94,"randomNumberQuery":2948,"popularity":84,"nbPlays":436,"themes":["mate","mateIn1","oneMove","opening","smotheredMate"],"gameUrl":"https://lichess.org/fW6HHmGP/black#17","openingFamily":"","openingVariation":"","__v":0},{"theme":"","_id":"65e8cbf7a5e6cd0e9beb5940","uid":"yeLGq","fen":"6Qk/6pp/pq3n1N/1p6/8/8/PP3PPP/2r2RK1 b - - 6 26","moves":"f6g8 h6f7","rating":1035,"ratingDeviation":100,"randomNumberQuery":1537,"popularity":76,"nbPlays":236,"themes":["endgame","mate","mateIn1","oneMove","smotheredMate"],"gameUrl":"https://lichess.org/ITNjg3Lr/black#51","openingFamily":"","openingVariation":"","__v":0},{"theme":"","_id":"65e8cbfca5e6cd0e9beb69dc","uid":"ygZNh","fen":"r1b3k1/1p5p/3p2p1/pB1Pp1Q1/4P3/P4N1n/1P4PP/2R3qK w - - 12 29","moves":"c1g1 h3f2","rating":1021,"ratingDeviation":93,"randomNumberQuery":6112,"popularity":50,"nbPlays":220,"themes":["mate","mateIn1","middlegame","oneMove","smotheredMate"],"gameUrl":"https://lichess.org/gIyHL6uZ#56","openingFamily":"","openingVariation":"","__v":0},{"theme":"","_id":"65e8cc1ea5e6cd0e9bebdf80","uid":"yvm6R","fen":"2r1r1Qk/6pp/p2R3N/1p6/8/7P/PP2bPP1/n5K1 b - - 8 30","moves":"e8g8 h6f7","rating":1032,"ratingDeviation":99,"randomNumberQuery":5257,"popularity":70,"nbPlays":152,"themes":["endgame","mate","mateIn1","oneMove","smotheredMate"],"gameUrl":"https://lichess.org/U6SwAtax/black#59","openingFamily":"","openingVariation":"","__v":0},{"theme":"","_id":"65e8cc45a5e6cd0e9bec6454","uid":"zDELc","fen":"4r3/R4pkp/1pQ5/5P2/2p5/7n/PPP3PP/5RqK w - - 6 31","moves":"f1g1 h3f2","rating":1026,"ratingDeviation":121,"randomNumberQuery":8708,"popularity":66,"nbPlays":133,"themes":["endgame","mate","mateIn1","oneMove","smotheredMate"],"gameUrl":"https://lichess.org/CLDEJv3Q#60","openingFamily":"","openingVariation":"","__v":0},{"theme":"","_id":"65e8cc4ca5e6cd0e9bec7bb6","uid":"zGEwx","fen":"r2qkb1r/pp1nnppp/4p3/1N1pP3/5BQ1/5B1P/PPP2PP1/R3K2R b KQkq - 6 12","moves":"g7g6 b5d6","rating":1022,"ratingDeviation":78,"randomNumberQuery":5310,"popularity":67,"nbPlays":148,"themes":["mate","mateIn1","middlegame","oneMove","smotheredMate"],"gameUrl":"https://lichess.org/K8TaLC4Y/black#23","openingFamily":"Sicilian_Defense","openingVariation":"Sicilian_Defense_Modern_Variations","__v":0},{"theme":"","_id":"65e8cc78a5e6cd0e9bed165e","uid":"zaRZj","fen":"Bnr3Qk/3b2pp/5b1N/5p2/p4P1P/3Pq3/1PP3P1/1K1R3R b - - 5 26","moves":"c8g8 h6f7","rating":1023,"ratingDeviation":91,"randomNumberQuery":43,"popularity":76,"nbPlays":397,"themes":["mate","mateIn1","middlegame","oneMove","smotheredMate"],"gameUrl":"https://lichess.org/UqexLzvr/black#51","openingFamily":"","openingVariation":"","__v":0},{"theme":"","_id":"65e8cc94a5e6cd0e9bed7af4","uid":"znhCW","fen":"rn1qkbnr/pp1bpppp/2p5/8/4N3/5N2/PPPPQPPP/R1B1KB1R b KQkq - 2 5","moves":"b8a6 e4d6","rating":1023,"ratingDeviation":76,"randomNumberQuery":613,"popularity":93,"nbPlays":522,"themes":["mate","mateIn1","oneMove","opening","pin","smotheredMate"],"gameUrl":"https://lichess.org/m6w84Ar3/black#9","openingFamily":"Caro-Kann_Defense","openingVariation":"Caro-Kann_Defense_Two_Knights_Attack","__v":0},{"theme":"","_id":"65e8cc96a5e6cd0e9bed7fd8","uid":"zoJ9V","fen":"k6r/6pp/p1N1p3/3ppb2/5P2/1NQ4n/rP4PP/2R3qK w - - 5 34","moves":"c1g1 h3f2","rating":1036,"ratingDeviation":105,"randomNumberQuery":3703,"popularity":69,"nbPlays":188,"themes":["mate","mateIn1","middlegame","oneMove","smotheredMate"],"gameUrl":"https://lichess.org/ZVU5QkxF#66","openingFamily":"","openingVariation":"","__v":0}]