[{"theme":"","_id":"65e8abbea5e6cd0e9b7b0b07","uid":"02SG5","fen":"r2q3k/3b1prQ/2pp1Nn1/ppnPp3/2P1P1P1/2N2P2/PP6/R3KB1R b KQ - 0 20","moves":"g7h7 h1h7","rating":1165,"ratingDeviation":101,"randomNumberQuery":5554,"popularity":50,"nbPlays":80,"themes":["arabianMate","kingsideAttack","mate","mateIn1","middlegame","oneMove"],"gameUrl":"https://lichess.org/N045WQfA/black#39","openingFamily":"","openingVariation":"","__v":0},{"theme":"","_id":"65e8abe0a5e6cd0e9b7b771e","uid":"0Gjvb","fen":"1k6/6R1/1P5p/5B2/5P2/5nP1/1r6/6K1 w - - 1 46","moves":"g1h1 b2h2","rating":1169,"ratingDeviation":89,"randomNumberQuery":2174,"popularity":100,"nbPlays":49,"themes":["arabianMate","endgame","mate","mateIn1","oneMove"],"gameUrl":"https://lichess.org/zNy6fs68#90","openingFamily":"","openingVariation":"","__v":0},{"theme":"","_id":"65e8ac1da5e6cd0e9b7c4ede","uid":"0jDAW","fen":"r2q2nk/pbpn2r1/1p1ppNpQ/8/3PP3/2NB4/PPP2PP1/R3K2R b KQ - 2 16","moves":"g8h6 h1h6 g7h7 h6h7","rating":1170,"ratingDeviation":78,"randomNumberQuery":1217,"popularity":56,"nbPlays":271,"themes":["arabianMate","kingsideAttack","mate","mateIn2","middlegame","short"],"gameUrl":"https://lichess.org/mcBSZy2I/black#31","openingFamily":"Owen_Defense","openingVariation":"Owen_Defense_Other_variations","__v":0},{"theme":"","_id":"65e8ac31a5e6cd0e9b7c95f2","uid":"0sUJc","fen":"r2q1rk1/ppp2p1p/5Np1/4pnP1/5n2/1b1P4/PPPQ1PP1/2KR2NR b - - 1 18","moves":"g8h8 h1h7","rating":1165,"ratingDeviation":76,"randomNumberQuery":1709,"popularity":96,"nbPlays":2068,"themes":["arabianMate","kingsideAttack","mate","mateIn1","oneMove","opening"],"gameUrl":"https://lichess.org/u01KuXKT/black#35","openingFamily":"Kings_Pawn_Game","openingVariation":"Kings_Pawn_Game_Wayward_Queen_Attack","__v":0},{"theme":"","_id":"65e8adf6a5e6cd0e9b82b21d","uid":"4AGKr","fen":"4R3/p1kp4/1p4Qp/5pn1/5p2/P4PrP/1P5K/8 w - - 2 46","moves":"g6f5 g5f3 h2h1 g3g1","rating":1160,"ratingDeviation":75,"randomNumberQuery":2537,"popularity":97,"nbPlays":3248,"themes":["arabianMate","endgame","mate","mateIn2","short"],"gameUrl":"https://lichess.org/bAY61C21#90","openingFamily":"","openingVariation":"","__v":0},{"theme":"","_id":"65e8ae19a5e6cd0e9b83326b","uid":"4R4L1","fen":"2b1r3/p1k3R1/1p5p/3pN3/2pP1r2/P7/1P5P/1K1R4 b - - 3 29","moves":"c7b8 e5c6 b8a8 g7a7","rating":1168,"ratingDeviation":117,"randomNumberQuery":8046,"popularity":65,"nbPlays":38,"themes":["arabianMate","endgame","mate","mateIn2","short"],"gameUrl":"https://lichess.org/kUNIAx4d/black#57","openingFamily":"","openingVariation":"","__v":0},{"theme":"","_id":"65e8ae1fa5e6cd0e9b8345df","uid":"4TgF4","fen":"r4r1k/1pp2p2/5NpB/nq2p2Q/7P/bPP3R1/P4PP1/1K1R4 b - - 1 22","moves":"a5b3 h6f8 g6h5 g3g8","rating":1162,"ratingDeviation":79,"randomNumberQuery":1120,"popularity":96,"nbPlays":21250,"themes":["arabianMate","discoveredAttack","kingsideAttack","mate","mateIn2","middlegame","sacrifice","short"],"gameUrl":"https://lichess.org/MNfYE6W3/black#43","openingFamily":"","openingVariation":"","__v":0},{"theme":"","_id":"65e8ae3aa5e6cd0e9b83a80d","uid":"4gbCw","fen":"r3k3/1p2pp2/1q1p3p/pPpP4/2P1b2B/1N3n2/1P1QBPr1/R4R1K w q - 2 24","moves":"d2c3 g2h2","rating":1162,"ratingDeviation":84,"randomNumberQuery":5245,"popularity":77,"nbPlays":103,"themes":["arabianMate","mate","mateIn1","middlegame","oneMove"],"gameUrl":"https://lichess.org/qWJJPjmE#46","openingFamily":"","openingVariation":"","__v":0},{"theme":"","_id":"65e8ae5ea5e6cd0e9b84282f","uid":"4xRlr","fen":"7k/ppR4p/4pN2/1b2P1r1/8/P7/6PP/6K1 b - - 1 29","moves":"g5e5 c7h7","rating":1173,"ratingDeviation":78,"randomNumberQuery":784,"popularity":91,"nbPlays":1441,"themes":["arabianMate","endgame","mate","mateIn1","oneMove"],"gameUrl":"https://lichess.org/2ttJ68zE/black#57","openingFamily":"","openingVariation":"","__v":0},{"theme":"","_id":"65e8aea6a5e6cd0e9b852be3","uid":"5VNj3","fen":"2r5/1p3p1k/p2p3b/5p1N/8/4PKR1/r4P2/8 b - - 1 33","moves":"c8c2 h5f6 h7h8 g3g8","rating":1178,"ratingDeviation":79,"randomNumberQuery":4272,"popularity":93,"nbPlays":860,"themes":["arabianMate","endgame","mate","mateIn2","short"],"gameUrl":"https://lichess.org/KWmsPhcg/black#65","openingFamily":"","openingVariation":"","__v":0},{"theme":"","_id":"65e8af8ea5e6cd0e9b885d43","uid":"7DvCB","fen":"3k4/2R5/1P1p4/3Pp1p1/4P2n/5PNP/1r6/5BK1 w - - 3 57","moves":"c7c6 h4f3 g1h1 b2h2","rating":1177,"ratingDeviation":88,"randomNumberQuery":841,"popularity":84,"nbPlays":277,"themes":["arabianMate","endgame","mate","mateIn2","short"],"gameUrl":"https://lichess.org/C5jZ9gBn#112","openingFamily":"","openingVariation":"","__v":0},{"theme":"","_id":"65e8b066a5e6cd0e9b8b4abe","uid":"8nsGI","fen":"8/5pkp/8/1RPPp1p1/4P1Pn/7P/r7/5BK1 w - - 1 53","moves":"c5c6 h4f3 g1h1 a2h2","rating":1161,"ratingDeviation":77,"randomNumberQuery":7498,"popularity":63,"nbPlays":79,"themes":["arabianMate","endgame","mate","mateIn2","short"],"gameUrl":"https://lichess.org/VNVEZEYG#104","openingFamily":"","openingVariation":"","__v":0},{"theme":"","_id":"65e8b09ca5e6cd0e9b8c06a2","uid":"9COmn","fen":"r5rk/pp2RQ2/5N1p/8/8/2qb3P/P4PPK/8 b - - 1 25","moves":"a8f8 f7h7 d3h7 e7h7","rating":1162,"ratingDeviation":80,"randomNumberQuery":5331,"popularity":92,"nbPlays":1791,"themes":["arabianMate","mate","mateIn2","middlegame","sacrifice","short"],"gameUrl":"https://lichess.org/3Brxf5Uv/black#49","openingFamily":"","openingVariation":"","__v":0},{"theme":"","_id":"65e8b11aa5e6cd0e9b8dc39c","uid":"A8BLv","fen":"5r2/pb1N1p1k/1p2p2p/1P6/P2PpP2/6RP/r5PK/8 b - - 3 33","moves":"f8g8 d7f6 h7h8 g3g8","rating":1173,"ratingDeviation":77,"randomNumberQuery":4963,"popularity":96,"nbPlays":18118,"themes":["arabianMate","endgame","fork","mate","mateIn2","short"],"gameUrl":"https://lichess.org/weMPvt2p/black#65","openingFamily":"","openingVariation":"","__v":0},{"theme":"","_id":"65e8b147a5e6cd0e9b8e6552","uid":"ATPke","fen":"rn3r1k/2qp1pnp/4pNP1/6P1/3N1P2/p3B3/1PPRB3/2K4R b - - 0 23","moves":"a3a2 h1h7","rating":1163,"ratingDeviation":75,"randomNumberQuery":191,"popularity":88,"nbPlays":1039,"themes":["arabianMate","kingsideAttack","mate","mateIn1","middlegame","oneMove"],"gameUrl":"https://lichess.org/rokaDofv/black#45","openingFamily":"","openingVariation":"","__v":0},{"theme":"","_id":"65e8b160a5e6cd0e9b8ebe8a","uid":"AfE7h","fen":"4N3/p6k/3p3b/2rP4/4p3/PK4R1/8/8 b - - 1 37","moves":"e4e3 e8f6 h7h8 g3g8","rating":1170,"ratingDeviation":75,"randomNumberQuery":9790,"popularity":93,"nbPlays":3900,"themes":["arabianMate","endgame","mate","mateIn2","short"],"gameUrl":"https://lichess.org/LsOqzKXG/black#73","openingFamily":"","openingVariation":"","__v":0},{"theme":"","_id":"65e8b1aea5e6cd0e9b8fc918","uid":"BE0di","fen":"8/5kpb/2p2p1p/4nP2/3BP3/2P3P1/r5BP/4R1K1 w - - 0 27","moves":"g2f1 e5f3 g1h1 a2h2","rating":1174,"ratingDeviation":81,"randomNumberQuery":8614,"popularity":85,"nbPlays":454,"themes":["arabianMate","endgame","fork","mate","mateIn2","short"],"gameUrl":"https://lichess.org/mSjVwS1D#52","openingFamily":"","openingVariation":"","__v":0},{"theme":"","_id":"65e8b1fea5e6cd0e9b90dd62","uid":"BoKW1","fen":"5RR1/6P1/8/2p3r1/1p1n4/3k3P/7K/8 w - - 0 52","moves":"f8c8 d4f3 h2h1 g5g1","rating":1176,"ratingDeviation":247,"randomNumberQuery":6761,"popularity":44,"nbPlays":8,"themes":["arabianMate","endgame","mate","mateIn2","short"],"gameUrl":"https://lichess.org/5zeBb4mD#102","openingFamily":"","openingVariation":"","__v":0},{"theme":"","_id":"65e8b29ea5e6cd0e9b930d6e","uid":"CzH0M","fen":"r7/3k1pQ1/2pp2p1/8/1p1P2P1/q1n2P2/bRP4P/K1N1R3 w - - 0 30","moves":"c1a2 a3a2 b2a2 a8a2","rating":1166,"ratingDeviation":77,"randomNumberQuery":5370,"popularity":97,"nbPlays":11340,"themes":["arabianMate","mate","mateIn2","middlegame","short"],"gameUrl":"https://lichess.org/IhOofZsz#58","openingFamily":"","openingVariation":"","__v":0},{"theme":"","_id":"65e8b2c6a5e6cd0e9b93917e","uid":"DGg0l","fen":"6k1/5pp1/4pN1p/1p2q3/1bp4Q/3r1P2/5P1P/6RK b - - 7 30","moves":"g8h8 h4h6 g7h6 g1g8","rating":1163,"ratingDeviation":83,"randomNumberQuery":4717,"popularity":87,"nbPlays":499,"themes":["arabianMate","endgame","mate","mateIn2","sacrifice","short"],"gameUrl":"https://lichess.org/e0O8oVxk/black#59","openingFamily":"","openingVariation":"","__v":0},{"theme":"","_id":"65e8b337a5e6cd0e9b950a49","uid":"E3wIe","fen":"6rk/pp1q1r1p/3pRN1Q/2p5/2P3R1/P4pPP/1P3P2/6K1 b - - 2 31","moves":"d7e6 g4g8","rating":1173,"ratingDeviation":78,"randomNumberQuery":2181,"popularity":93,"nbPlays":2462,"themes":["arabianMate","endgame","kingsideAttack","mate","mateIn1","oneMove"],"gameUrl":"https://lichess.org/85OHFPvC/black#61","openingFamily":"","openingVariation":"","__v":0},{"theme":"","_id":"65e8b423a5e6cd0e9b983195","uid":"Flfy1","fen":"5R2/6pp/5p1k/P7/1B6/2P2nrP/6r1/6RK w - - 0 36","moves":"g1g2 g3h3 g2h2 h3h2","rating":1174,"ratingDeviation":79,"randomNumberQuery":6753,"popularity":77,"nbPlays":241,"themes":["arabianMate","endgame","mate","mateIn2","short"],"gameUrl":"https://lichess.org/2J5qTjrO#70","openingFamily":"","openingVariation":"","__v":0},{"theme":"","_id":"65e8b46ba5e6cd0e9b99323d","uid":"GJFId","fen":"r6k/p1p2p1p/1q3N2/8/3N3R/7P/3r2P1/5R1K b - - 5 32","moves":"d2d4 h4h7","rating":1174,"ratingDeviation":82,"randomNumberQuery":4527,"popularity":55,"nbPlays":107,"themes":["arabianMate","endgame","mate","mateIn1","oneMove"],"gameUrl":"https://lichess.org/vw902cRS/black#63","openingFamily":"","openingVariation":"","__v":0},{"theme":"","_id":"65e8b492a5e6cd0e9b99b9a3","uid":"GawRg","fen":"5rk1/3N1ppp/4p3/1p1p2Q1/2nP2P1/p3P1P1/3q1PK1/7R b - - 1 28","moves":"a3a2 d7f6 g8h8 h1h7","rating":1179,"ratingDeviation":75,"randomNumberQuery":3971,"popularity":96,"nbPlays":9341,"themes":["arabianMate","endgame","kingsideAttack","mate","mateIn2","pin","short"],"gameUrl":"https://lichess.org/YIAvivOB/black#55","openingFamily":"","openingVariation":"","__v":0},{"theme":"","_id":"65e8b5b5a5e6cd0e9b9dcb20","uid":"In4Ld","fen":"4r2k/5p1p/r2p1Nq1/2n1pN2/p3P3/P4P1Q/1Pp3P1/2K4R b - - 1 29","moves":"e8c8 h3h7 g6h7 h1h7","rating":1167,"ratingDeviation":77,"randomNumberQuery":7519,"popularity":93,"nbPlays":1436,"themes":["arabianMate","kingsideAttack","mate","mateIn2","middlegame","short"],"gameUrl":"https://lichess.org/blcauURx/black#57","openingFamily":"","openingVariation":"","__v":0},{"theme":"","_id":"65e8b6b8a5e6cd0e9ba16112","uid":"KjZrI","fen":"r5k1/1pp2p1p/6p1/8/n2PP1P1/q1P4P/P1RQ4/1K5R w - - 0 30","moves":"d2c1 a4c3 b1a1 a3a2 c2a2 a8a2","rating":1176,"ratingDeviation":77,"randomNumberQuery":9930,"popularity":92,"nbPlays":1434,"themes":["arabianMate","endgame","long","mate","mateIn3","queensideAttack","sacrifice"],"gameUrl":"https://lichess.org/LT8UyZFq#58","openingFamily":"","openingVariation":"","__v":0},{"theme":"","_id":"65e8b6d7a5e6cd0e9ba1d2ea","uid":"Kyaia","fen":"1r6/8/4Q3/8/3k4/2n5/1PP1RPP1/1K6 w - - 1 39","moves":"b1a1 b8a8 e6a2 a8a2","rating":1160,"ratingDeviation":80,"randomNumberQuery":650,"popularity":88,"nbPlays":215,"themes":["arabianMate","endgame","mate","mateIn2","short"],"gameUrl":"https://lichess.org/lKz0i5JS#76","openingFamily":"","openingVariation":"","__v":0},{"theme":"","_id":"65e8b71aa5e6cd0e9ba2bb01","uid":"LTD3d","fen":"3q3k/p4prp/2b1rN1Q/4p3/1npp3R/5R2/1PP2PPP/3B2K1 b - - 7 33","moves":"c6f3 h6h7 g7h7 h4h7","rating":1178,"ratingDeviation":97,"randomNumberQuery":9505,"popularity":65,"nbPlays":110,"themes":["arabianMate","kingsideAttack","mate","mateIn2","middlegame","sacrifice","short"],"gameUrl":"https://lichess.org/wTsKq1pM/black#65","openingFamily":"","openingVariation":"","__v":0},{"theme":"","_id":"65e8b740a5e6cd0e9ba33da1","uid":"LkLX4","fen":"2r3k1/pp1R3p/6pB/4p3/4N1P1/1K6/2r5/4n3 b - - 7 33","moves":"e1f3 e4f6 g8h8 d7h7","rating":1170,"ratingDeviation":77,"randomNumberQuery":4674,"popularity":91,"nbPlays":412,"themes":["arabianMate","endgame","mate","mateIn2","short"],"gameUrl":"https://lichess.org/SwD0LuLr/black#65","openingFamily":"","openingVariation":"","__v":0},{"theme":"","_id":"65e8b764a5e6cd0e9ba3bc13","uid":"M0iNe","fen":"6k1/6pp/b3p3/p3p3/P1PnP3/1n1P1PP1/3r3P/1R1Q1BK1 w - - 5 29","moves":"d1b3 d4f3 g1h1 d2h2","rating":1164,"ratingDeviation":75,"randomNumberQuery":3301,"popularity":94,"nbPlays":1649,"themes":["arabianMate","endgame","kingsideAttack","mate","mateIn2","short"],"gameUrl":"https://lichess.org/PuLGogDY#56","openingFamily":"","openingVariation":"","__v":0},{"theme":"","_id":"65e8b78fa5e6cd0e9ba44f49","uid":"MJvFb","fen":"5k2/1p1R4/p4p2/6p1/P2P1P1n/8/1r5P/5BK1 w - - 1 34","moves":"f4g5 h4f3 g1h1 b2h2","rating":1171,"ratingDeviation":75,"randomNumberQuery":4180,"popularity":96,"nbPlays":7637,"themes":["arabianMate","endgame","mate","mateIn2","short"],"gameUrl":"https://lichess.org/Ps77WvJP#66","openingFamily":"","openingVariation":"","__v":0},{"theme":"","_id":"65e8b7eaa5e6cd0e9ba58edb","uid":"MzYxM","fen":"6k1/5p1p/pR4p1/3P4/3n1P1P/6P1/PPr2K2/5B2 w - - 1 34","moves":"f2g1 d4f3 g1h1 c2h2","rating":1170,"ratingDeviation":86,"randomNumberQuery":4671,"popularity":75,"nbPlays":79,"themes":["arabianMate","endgame","mate","mateIn2","short"],"gameUrl":"https://lichess.org/lR2aOPnZ#66","openingFamily":"","openingVariation":"","__v":0},{"theme":"","_id":"65e8b89aa5e6cd0e9ba806f7","uid":"OKPQc","fen":"3r2Rk/pp2r3/5N1p/8/5p2/3p1B2/PP3b1P/6RK b - - 1 34","moves":"d8g8 g1g8","rating":1164,"ratingDeviation":149,"randomNumberQuery":5638,"popularity":100,"nbPlays":16,"themes":["arabianMate","endgame","mate","mateIn1","oneMove"],"gameUrl":"https://lichess.org/3Och0GT3/black#67","openingFamily":"","openingVariation":"","__v":0},{"theme":"","_id":"65e8b8e8a5e6cd0e9ba91d12","uid":"OuYUF","fen":"3r4/kp4p1/1b3p1p/6P1/PPQn3N/3P2P1/4r1KP/R4R2 w - - 1 28","moves":"g2g1 d4f3 g1h1 e2h2","rating":1175,"ratingDeviation":76,"randomNumberQuery":8949,"popularity":93,"nbPlays":2790,"themes":["arabianMate","doubleCheck","kingsideAttack","mate","mateIn2","middlegame","short"],"gameUrl":"https://lichess.org/pknfIAu4#54","openingFamily":"","openingVariation":"","__v":0},{"theme":"","_id":"65e8b8efa5e6cd0e9ba934aa","uid":"OxbdW","fen":"6k1/5R2/3NpN1p/3p4/q1pn1P2/8/5KPP/8 b - - 4 34","moves":"g8h8 f7h7","rating":1161,"ratingDeviation":79,"randomNumberQuery":7812,"popularity":91,"nbPlays":896,"themes":["arabianMate","endgame","mate","mateIn1","oneMove"],"gameUrl":"https://lichess.org/YkoQEqs6/black#67","openingFamily":"","openingVariation":"","__v":0},{"theme":"","_id":"65e8b962a5e6cd0e9baacaa0","uid":"PonUK","fen":"r3k1nr/1p1b4/pq2p3/2bpPp2/1P4p1/P1NBBnP1/7P/R2QNR1K w kq - 1 20","moves":"e3c5 h8h2","rating":1170,"ratingDeviation":75,"randomNumberQuery":1368,"popularity":92,"nbPlays":1770,"themes":["arabianMate","kingsideAttack","mate","mateIn1","middlegame","oneMove"],"gameUrl":"https://lichess.org/5Nn74KaM#38","openingFamily":"","openingVariation":"","__v":0},{"theme":"","_id":"65e8b972a5e6cd0e9bab0290","uid":"Pw5Ha","fen":"8/2k5/1r6/2n1p3/p3n3/P1P1B2B/K2R4/8 w - - 12 45","moves":"e3c5 e4c3 a2a1 b6b1","rating":1179,"ratingDeviation":76,"randomNumberQuery":7420,"popularity":95,"nbPlays":6366,"themes":["arabianMate","endgame","mate","mateIn2","short"],"gameUrl":"https://lichess.org/Ejk7maRs#88","openingFamily":"","openingVariation":"","__v":0},{"theme":"","_id":"65e8b983a5e6cd0e9bab3de0","uid":"Q3wju","fen":"5rk1/p1p4p/1p1p1r2/3P2p1/4P3/2P1Qnq1/P3BR1P/5R1K w - - 0 30","moves":"h2g3 f6h6 f2h2 h6h2","rating":1174,"ratingDeviation":80,"randomNumberQuery":44,"popularity":58,"nbPlays":326,"themes":["arabianMate","kingsideAttack","mate","mateIn2","middlegame","short"],"gameUrl":"https://lichess.org/bd3JH6k5#58","openingFamily":"","openingVariation":"","__v":0},{"theme":"","_id":"65e8b9aea5e6cd0e9babd68a","uid":"QO0fN","fen":"1k3r2/pp5p/4B1p1/3p2B1/3P4/2P2n1P/PP3r1P/R3R2K w - - 4 27","moves":"e1f1 f2h2","rating":1178,"ratingDeviation":77,"randomNumberQuery":364,"popularity":90,"nbPlays":683,"themes":["arabianMate","kingsideAttack","mate","mateIn1","middlegame","oneMove"],"gameUrl":"https://lichess.org/44QqiEwb#52","openingFamily":"","openingVariation":"","__v":0},{"theme":"","_id":"65e8b9e8a5e6cd0e9baca325","uid":"QooL4","fen":"rn1q3k/p3nr1p/1b1p1N2/2pPpP2/6PQ/P6R/4b1BP/R1B3K1 b - - 1 22","moves":"e7f5 h4h7 f7h7 h3h7","rating":1162,"ratingDeviation":83,"randomNumberQuery":2264,"popularity":81,"nbPlays":210,"themes":["arabianMate","kingsideAttack","mate","mateIn2","middlegame","sacrifice","short"],"gameUrl":"https://lichess.org/H9j09zpF/black#43","openingFamily":"","openingVariation":"","__v":0},{"theme":"","_id":"65e8baaba5e6cd0e9baf5107","uid":"SGM6X","fen":"8/1p1RR3/p3pk2/P6p/6pP/5nP1/2r4r/5N1K w - - 2 43","moves":"f1h2 c2h2","rating":1170,"ratingDeviation":82,"randomNumberQuery":3132,"popularity":82,"nbPlays":976,"themes":["arabianMate","endgame","mate","mateIn1","oneMove"],"gameUrl":"https://lichess.org/GSYAtj5Z#84","openingFamily":"","openingVariation":"","__v":0},{"theme":"","_id":"65e8bab6a5e6cd0e9baf7a03","uid":"SLdvN","fen":"2k5/6Rp/R7/4Pp2/3p4/5n2/3r4/6K1 w - - 2 43","moves":"g1h1 d2h2","rating":1161,"ratingDeviation":80,"randomNumberQuery":2159,"popularity":90,"nbPlays":510,"themes":["arabianMate","endgame","mate","mateIn1","oneMove"],"gameUrl":"https://lichess.org/U5uOlShR#84","openingFamily":"","openingVariation":"","__v":0},{"theme":"","_id":"65e8baf6a5e6cd0e9bb05b09","uid":"SoxIx","fen":"r1b1r1Rk/pp1q4/5N2/4Pp1p/2p1Q2P/8/PP3P2/2K3R1 b - - 1 28","moves":"e8g8 g1g8","rating":1160,"ratingDeviation":78,"randomNumberQuery":2023,"popularity":94,"nbPlays":4144,"themes":["arabianMate","mate","mateIn1","middlegame","oneMove"],"gameUrl":"https://lichess.org/TQY04Lqu/black#55","openingFamily":"","openingVariation":"","__v":0},{"theme":"","_id":"65e8bb32a5e6cd0e9bb12d65","uid":"TGZg7","fen":"r2q1r1k/3pRP1p/2p1nNbQ/p7/1p6/2P4R/PP4PP/7K b - - 6 31","moves":"d8e7 h6h7 g6h7 h3h7","rating":1173,"ratingDeviation":79,"randomNumberQuery":5592,"popularity":92,"nbPlays":4036,"themes":["arabianMate","kingsideAttack","mate","mateIn2","middlegame","sacrifice","short"],"gameUrl":"https://lichess.org/Ryv2HAny/black#61","openingFamily":"","openingVariation":"","__v":0},{"theme":"","_id":"65e8bca9a5e6cd0e9bb655ca","uid":"W351s","fen":"5r1k/2p1n1r1/4BNp1/p1p1P1np/5P2/2PPK3/P4P1R/7R b - - 0 32","moves":"g5e6 h2h5 g6h5 h1h5 g7h7 h5h7","rating":1161,"ratingDeviation":83,"randomNumberQuery":1447,"popularity":87,"nbPlays":2649,"themes":["arabianMate","exposedKing","kingsideAttack","long","mate","mateIn3","middlegame","sacrifice"],"gameUrl":"https://lichess.org/WCNf59xK/black#63","openingFamily":"","openingVariation":"","__v":0},{"theme":"","_id":"65e8bcd0a5e6cd0e9bb6dff4","uid":"WL5GH","fen":"6rk/pp5p/5br1/3P1N2/PP2Pp2/5n2/2RB1P1P/5R1K w - - 0 29","moves":"d2f4 g6g1 f1g1 g8g1","rating":1160,"ratingDeviation":101,"randomNumberQuery":7384,"popularity":67,"nbPlays":94,"themes":["arabianMate","mate","mateIn2","middlegame","short"],"gameUrl":"https://lichess.org/CVWfKE5q#56","openingFamily":"","openingVariation":"","__v":0},{"theme":"","_id":"65e8bd58a5e6cd0e9bb8b310","uid":"XKLrU","fen":"3rr1k1/pp3ppp/8/2p4Q/8/N1P2nPP/PP4R1/R2q3K w - - 6 22","moves":"a1d1 d8d1 g2g1 d1g1","rating":1166,"ratingDeviation":81,"randomNumberQuery":5577,"popularity":90,"nbPlays":911,"themes":["arabianMate","kingsideAttack","mate","mateIn2","middlegame","short"],"gameUrl":"https://lichess.org/Vvru7Bdh#42","openingFamily":"","openingVariation":"","__v":0},{"theme":"","_id":"65e8beada5e6cd0e9bbd5a90","uid":"Zpn00","fen":"r5r1/1pN1k2p/3p4/3Pp3/2Q2pq1/5n2/PB3R1P/R6K w - - 3 31","moves":"c7a8 g4g1 a1g1 g8g1","rating":1174,"ratingDeviation":82,"randomNumberQuery":5105,"popularity":80,"nbPlays":200,"themes":["arabianMate","mate","mateIn2","middlegame","sacrifice","short"],"gameUrl":"https://lichess.org/9k6Be5aq#60","openingFamily":"","openingVariation":"","__v":0},{"theme":"","_id":"65e8bf42a5e6cd0e9bbf68fa","uid":"awQRe","fen":"6r1/pRR2p2/3kp3/3pn3/8/5P1P/P4P1K/8 w - - 1 32","moves":"b7a7 e5f3 h2h1 g8g1","rating":1160,"ratingDeviation":245,"randomNumberQuery":771,"popularity":44,"nbPlays":10,"themes":["arabianMate","endgame","mate","mateIn2","short"],"gameUrl":"https://lichess.org/0oVq8gOp#62","openingFamily":"","openingVariation":"","__v":0},{"theme":"","_id":"65e8bf53a5e6cd0e9bbfa436","uid":"b48IW","fen":"1nbqr2k/6rQ/p4Np1/2p5/2B1P3/5P2/PpP3P1/1K1R3R b - - 0 22","moves":"g7h7 h1h7","rating":1171,"ratingDeviation":83,"randomNumberQuery":2111,"popularity":73,"nbPlays":369,"themes":["arabianMate","kingsideAttack","mate","mateIn1","middlegame","oneMove"],"gameUrl":"https://lichess.org/GZm4XRyx/black#43","openingFamily":"","openingVariation":"","__v":0},{"theme":"","_id":"65e8bfaaa5e6cd0e9bc0dd2e","uid":"bj6lp","fen":"r3N1k1/4R1b1/p5pp/5p2/5B2/1p4P1/b4P1P/6K1 b - - 1 33","moves":"g7f8 e8f6 g8h8 e7h7","rating":1173,"ratingDeviation":83,"randomNumberQuery":7405,"popularity":88,"nbPlays":941,"themes":["arabianMate","endgame","mate","mateIn2","short"],"gameUrl":"https://lichess.org/fuc8nM3v/black#65","openingFamily":"","openingVariation":"","__v":0},{"theme":"","_id":"65e8bfdea5e6cd0e9bc193e6","uid":"c6wkI","fen":"7k/p5qp/1p1b1Nn1/n1p1p1r1/2Pp1p2/P2P1P2/1PK1P2Q/6RR b - - 9 30","moves":"g5g1 h2h7 g7h7 h1h7","rating":1170,"ratingDeviation":76,"randomNumberQuery":3586,"popularity":82,"nbPlays":161,"themes":["arabianMate","kingsideAttack","mate","mateIn2","middlegame","short"],"gameUrl":"https://lichess.org/IZpXUKt6/black#59","openingFamily":"","openingVariation":"","__v":0},{"theme":"","_id":"65e8c0b3a5e6cd0e9bc47fb3","uid":"dgdV3","fen":"5r1k/p1p3pp/1p1p4/3P1p1q/PP4P1/2P2n2/2QNr3/R4R1K w - - 0 24","moves":"g4h5 e2h2","rating":1169,"ratingDeviation":253,"randomNumberQuery":2507,"popularity":67,"nbPlays":16,"themes":["arabianMate","mate","mateIn1","middlegame","oneMove"],"gameUrl":"https://lichess.org/eDIn9s5y#46","openingFamily":"","openingVariation":"","__v":0},{"theme":"","_id":"65e8c0daa5e6cd0e9bc50b15","uid":"dyZ9s","fen":"r6k/1pp5/3p3B/p2Pp3/2P5/P4nP1/1P3r2/1R1R3K w - - 0 27","moves":"d1f1 f2h2","rating":1164,"ratingDeviation":84,"randomNumberQuery":4086,"popularity":87,"nbPlays":625,"themes":["arabianMate","endgame","mate","mateIn1","oneMove"],"gameUrl":"https://lichess.org/vp73fe2Z#52","openingFamily":"","openingVariation":"","__v":0},{"theme":"","_id":"65e8c0efa5e6cd0e9bc55549","uid":"e8Mln","fen":"6rk/1bp1qprp/pp1p1N1Q/4nP2/2P1P2R/3P3P/PP6/R6K b - - 0 27","moves":"e5d3 h6h7 g7h7 h4h7","rating":1163,"ratingDeviation":86,"randomNumberQuery":4019,"popularity":80,"nbPlays":198,"themes":["arabianMate","kingsideAttack","mate","mateIn2","middlegame","sacrifice","short"],"gameUrl":"https://lichess.org/j41JM5hm/black#53","openingFamily":"","openingVariation":"","__v":0},{"theme":"","_id":"65e8c0fea5e6cd0e9bc58a4f","uid":"eFLIY","fen":"5bk1/1R1N3p/p3pp2/3b4/8/1p2PP1P/2r3P1/6K1 b - - 1 32","moves":"b3b2 d7f6 g8h8 b7h7","rating":1161,"ratingDeviation":94,"randomNumberQuery":9902,"popularity":71,"nbPlays":76,"themes":["arabianMate","discoveredAttack","endgame","mate","mateIn2","short"],"gameUrl":"https://lichess.org/luEOyvlR/black#63","openingFamily":"","openingVariation":"","__v":0},{"theme":"","_id":"65e8c105a5e6cd0e9bc5a21f","uid":"eIWSn","fen":"8/5ppk/2p1p2Q/p1PpP3/3Pb1N1/P5RP/5PPK/1q3r2 b - - 0 33","moves":"g7h6 g4f6 h7h8 g3g8","rating":1168,"ratingDeviation":87,"randomNumberQuery":7291,"popularity":78,"nbPlays":146,"themes":["arabianMate","endgame","mate","mateIn2","short"],"gameUrl":"https://lichess.org/I9ELiVnk/black#65","openingFamily":"","openingVariation":"","__v":0},{"theme":"","_id":"65e8c174a5e6cd0e9bc71bef","uid":"f6497","fen":"7k/5R1p/5Npb/2B1P3/P7/3P2PK/rp1n4/8 b - - 1 35","moves":"b2b1q f7h7","rating":1170,"ratingDeviation":81,"randomNumberQuery":6081,"popularity":81,"nbPlays":231,"themes":["arabianMate","mate","mateIn1","middlegame","oneMove"],"gameUrl":"https://lichess.org/FiUNBjdp/black#69","openingFamily":"","openingVariation":"","__v":0},{"theme":"","_id":"65e8c180a5e6cd0e9bc746eb","uid":"fBhjz","fen":"2k5/pp4Rp/5N2/8/2P5/1P3n1P/P2r3P/7K w - - 1 28","moves":"g7h7 d2h2","rating":1160,"ratingDeviation":79,"randomNumberQuery":5782,"popularity":89,"nbPlays":1425,"themes":["arabianMate","endgame","mate","mateIn1","oneMove"],"gameUrl":"https://lichess.org/au9A5uXc#54","openingFamily":"","openingVariation":"","__v":0},{"theme":"","_id":"65e8c262a5e6cd0e9bca479c","uid":"goBnX","fen":"4r2k/p1p3pp/7r/8/1P6/P3PnP1/1B2NP1q/R4RQK w - - 0 26","moves":"g1h2 h6h2","rating":1163,"ratingDeviation":82,"randomNumberQuery":6864,"popularity":83,"nbPlays":444,"themes":["arabianMate","mate","mateIn1","middlegame","oneMove"],"gameUrl":"https://lichess.org/VwxT693r#50","openingFamily":"","openingVariation":"","__v":0},{"theme":"","_id":"65e8c387a5e6cd0e9bce4c3a","uid":"iyK7s","fen":"8/pppR1Ppk/8/5N2/5b2/P4nPP/1Pr5/7K w - - 1 38","moves":"f7f8q c2h2","rating":1169,"ratingDeviation":75,"randomNumberQuery":6369,"popularity":96,"nbPlays":12349,"themes":["arabianMate","endgame","master","mate","mateIn1","oneMove"],"gameUrl":"https://lichess.org/fWJenBpJ#74","openingFamily":"","openingVariation":"","__v":0},{"theme":"","_id":"65e8c3d5a5e6cd0e9bcf5faf","uid":"jYKfv","fen":"2R1N2k/r5p1/p4p1p/8/8/P2n3P/bP3PP1/4R1K1 b - - 2 33","moves":"d3e1 e8f6 a2g8 c8g8","rating":1168,"ratingDeviation":78,"randomNumberQuery":1827,"popularity":88,"nbPlays":469,"themes":["arabianMate","discoveredAttack","endgame","mate","mateIn2","short"],"gameUrl":"https://lichess.org/JgiVG9M0/black#65","openingFamily":"","openingVariation":"","__v":0},{"theme":"","_id":"65e8c427a5e6cd0e9bd07c67","uid":"k9guw","fen":"3q1rk1/1pp4p/3pNbpP/5p2/p5P1/P1nQB3/1rP2P2/K2R1B1R w - - 0 21","moves":"e6d8 b2a2","rating":1175,"ratingDeviation":82,"randomNumberQuery":8218,"popularity":82,"nbPlays":1179,"themes":["arabianMate","mate","mateIn1","middlegame","oneMove"],"gameUrl":"https://lichess.org/bhcWPnz8#40","openingFamily":"","openingVariation":"","__v":0},{"theme":"","_id":"65e8c467a5e6cd0e9bd15b72","uid":"kck2z","fen":"R7/8/8/P3n1k1/8/6p1/r7/5BK1 w - - 2 59","moves":"a5a6 e5f3 g1h1 a2h2","rating":1170,"ratingDeviation":81,"randomNumberQuery":3921,"popularity":80,"nbPlays":499,"themes":["arabianMate","endgame","mate","mateIn2","short"],"gameUrl":"https://lichess.org/M0hVkqfY#116","openingFamily":"","openingVariation":"","__v":0},{"theme":"","_id":"65e8c4d9a5e6cd0e9bd2e43f","uid":"lS65L","fen":"4n1r1/1RP3rk/2Pp3b/3Pp2p/4Pp2/2N2n1N/5B1P/4QBqK w - - 1 35","moves":"h3g1 g7g1 f2g1 g8g1","rating":1171,"ratingDeviation":81,"randomNumberQuery":8907,"popularity":88,"nbPlays":271,"themes":["arabianMate","kingsideAttack","mate","mateIn2","middlegame","short"],"gameUrl":"https://lichess.org/gGwNlIez#68","openingFamily":"","openingVariation":"","__v":0},{"theme":"","_id":"65e8c519a5e6cd0e9bd3ca41","uid":"lvsXr","fen":"r2r3k/5p2/4p3/3p1P1P/1p1P4/qPnQ4/P1R1B3/K6R w - - 1 37","moves":"d3e3 a3a2 c2a2 a8a2","rating":1174,"ratingDeviation":83,"randomNumberQuery":9516,"popularity":89,"nbPlays":1496,"themes":["arabianMate","mate","mateIn2","middlegame","sacrifice","short"],"gameUrl":"https://lichess.org/yvmxds8l#72","openingFamily":"","openingVariation":"","__v":0},{"theme":"","_id":"65e8c569a5e6cd0e9bd4e28e","uid":"mWiVb","fen":"6k1/1R3p2/1p6/6n1/7p/1P4rP/P1R4K/8 w - - 0 36","moves":"b7b6 g5f3 h2h1 g3g1","rating":1165,"ratingDeviation":76,"randomNumberQuery":2225,"popularity":95,"nbPlays":4932,"themes":["arabianMate","endgame","mate","mateIn2","short"],"gameUrl":"https://lichess.org/RuMuerY9#70","openingFamily":"","openingVariation":"","__v":0},{"theme":"","_id":"65e8c590a5e6cd0e9bd5628f","uid":"mnaeZ","fen":"2r4k/6R1/4pN1p/p2pP1pN/1p1P2Pb/4P2K/PPq4P/8 b - - 4 41","moves":"c2f2 g7h7","rating":1166,"ratingDeviation":80,"randomNumberQuery":2168,"popularity":84,"nbPlays":417,"themes":["arabianMate","endgame","mate","mateIn1","oneMove"],"gameUrl":"https://lichess.org/Hql0czlc/black#81","openingFamily":"","openingVariation":"","__v":0},{"theme":"","_id":"65e8c59ea5e6cd0e9bd591ed","uid":"mtkxk","fen":"7k/6p1/R2B4/P1P4P/8/5n2/2r5/7K w - - 1 41","moves":"d6h2 c2h2","rating":1161,"ratingDeviation":80,"randomNumberQuery":6627,"popularity":92,"nbPlays":1662,"themes":["arabianMate","endgame","master","mate","mateIn1","oneMove"],"gameUrl":"https://lichess.org/pFA8cEjH#80","openingFamily":"","openingVariation":"","__v":0},{"theme":"","_id":"65e8c67aa5e6cd0e9bd86e17","uid":"oRKyq","fen":"5r1k/2p2pR1/3p3p/7r/4P3/1B2Bn1q/PP3P1P/R5QK w - - 1 25","moves":"g1g2 h3h2 g2h2 h5h2","rating":1172,"ratingDeviation":80,"randomNumberQuery":956,"popularity":88,"nbPlays":774,"themes":["arabianMate","kingsideAttack","mate","mateIn2","middlegame","short"],"gameUrl":"https://lichess.org/RVQGEVsz#48","openingFamily":"","openingVariation":"","__v":0},{"theme":"","_id":"65e8c7a0a5e6cd0e9bdc5aa9","uid":"qZ6BW","fen":"r2qk2r/bppb1pp1/p2p1B2/3N4/2P5/1P3nN1/P5BP/R2Q1RK1 w kq - 0 16","moves":"g1h1 h8h2","rating":1167,"ratingDeviation":81,"randomNumberQuery":1341,"popularity":47,"nbPlays":126,"themes":["arabianMate","kingsideAttack","mate","mateIn1","oneMove","opening"],"gameUrl":"https://lichess.org/ifUZeT3K#30","openingFamily":"English_Opening","openingVariation":"English_Opening_Kings_English_Variation","__v":0},{"theme":"","_id":"65e8c7bea5e6cd0e9bdcca67","uid":"qngwJ","fen":"5bk1/1R6/6n1/7N/3r4/1P6/8/1K6 b - - 0 47","moves":"d4b4 h5f6 g8h8 b7h7","rating":1164,"ratingDeviation":74,"randomNumberQuery":7082,"popularity":96,"nbPlays":9583,"themes":["arabianMate","endgame","master","mate","mateIn2","short"],"gameUrl":"https://lichess.org/opqmpId5/black#93","openingFamily":"","openingVariation":"","__v":0},{"theme":"","_id":"65e8c80ca5e6cd0e9bdddfd1","uid":"rNfyS","fen":"7k/p4rQ1/2p2N1p/1p2pP2/1q2P3/n3P3/2P3R1/2K4R b - - 0 39","moves":"f7g7 h1h6 g7h7 h6h7","rating":1175,"ratingDeviation":76,"randomNumberQuery":9223,"popularity":90,"nbPlays":1123,"themes":["arabianMate","endgame","mate","mateIn2","short"],"gameUrl":"https://lichess.org/t43ab87E/black#77","openingFamily":"","openingVariation":"","__v":0},{"theme":"","_id":"65e8c85ca5e6cd0e9bdef83f","uid":"ryHJ8","fen":"1r6/p2N3k/8/P1pp1p1P/4b3/2P1P3/r7/2R1K1R1 b - - 2 36","moves":"b8b2 d7f6 h7h8 g1g8","rating":1177,"ratingDeviation":82,"randomNumberQuery":8290,"popularity":85,"nbPlays":3109,"themes":["arabianMate","endgame","mate","mateIn2","short"],"gameUrl":"https://lichess.org/tCwxoHTP/black#71","openingFamily":"","openingVariation":"","__v":0},{"theme":"","_id":"65e8c87aa5e6cd0e9bdf62d3","uid":"sC8YR","fen":"6r1/pq4k1/3p2R1/3Np1K1/2P1P1P1/3P1p2/P3nP2/8 b - - 3 32","moves":"g7h7 d5f6 h7h8 g6g8","rating":1171,"ratingDeviation":83,"randomNumberQuery":2777,"popularity":83,"nbPlays":179,"themes":["arabianMate","endgame","fork","mate","mateIn2","short"],"gameUrl":"https://lichess.org/XJdPUJmL/black#63","openingFamily":"","openingVariation":"","__v":0},{"theme":"","_id":"65e8c881a5e6cd0e9bdf7a91","uid":"sFCXF","fen":"r4rk1/2p2ppp/3p4/p1p5/4N3/PP5R/2P1Nq2/2K3R1 b - - 1 23","moves":"f2e2 e4f6 g8h8 h3h7","rating":1166,"ratingDeviation":109,"randomNumberQuery":7331,"popularity":82,"nbPlays":43,"themes":["arabianMate","endgame","mate","mateIn2","pin","short"],"gameUrl":"https://lichess.org/fg3E4p9j/black#45","openingFamily":"","openingVariation":"","__v":0},{"theme":"","_id":"65e8c8b9a5e6cd0e9be03d70","uid":"seVmm","fen":"1k5r/1p1r2p1/5p2/2Pqp3/1R6/4Nnp1/5P1P/QR5K w - - 0 27","moves":"e3d5 h8h2","rating":1167,"ratingDeviation":77,"randomNumberQuery":3263,"popularity":91,"nbPlays":3170,"themes":["arabianMate","mate","mateIn1","middlegame","oneMove"],"gameUrl":"https://lichess.org/MHQj3lyS#52","openingFamily":"","openingVariation":"","__v":0},{"theme":"","_id":"65e8c8c6a5e6cd0e9be06af2","uid":"skKu9","fen":"6rk/1pp2p1p/p2p4/3P4/4P1r1/2P2n2/PPB1RQ1P/5q1K w - - 0 29","moves":"f2f1 g4g1 f1g1 g8g1","rating":1163,"ratingDeviation":81,"randomNumberQuery":1725,"popularity":80,"nbPlays":436,"themes":["arabianMate","endgame","fork","mate","mateIn2","short"],"gameUrl":"https://lichess.org/0oKt8cwv#56","openingFamily":"","openingVariation":"","__v":0},{"theme":"","_id":"65e8c8e8a5e6cd0e9be0e2aa","uid":"t00ql","fen":"8/p7/1kp5/8/8/1P3n1P/P1Qr4/7K w - - 3 49","moves":"c2e4 d2h2","rating":1177,"ratingDeviation":83,"randomNumberQuery":4978,"popularity":78,"nbPlays":577,"themes":["arabianMate","endgame","mate","mateIn1","oneMove"],"gameUrl":"https://lichess.org/hfoi9bRZ#96","openingFamily":"","openingVariation":"","__v":0},{"theme":"","_id":"65e8c8fca5e6cd0e9be12934","uid":"t97Il","fen":"r1b4k/1p4rp/3p1N1Q/p3p3/2P1P1P1/P4q2/1P6/4KB1R b K - 1 28","moves":"c8g4 h6h7 g7h7 h1h7","rating":1167,"ratingDeviation":82,"randomNumberQuery":3886,"popularity":63,"nbPlays":199,"themes":["arabianMate","mate","mateIn2","middlegame","sacrifice","short"],"gameUrl":"https://lichess.org/paPY01Zo/black#55","openingFamily":"","openingVariation":"","__v":0},{"theme":"","_id":"65e8c925a5e6cd0e9be1b118","uid":"tQljy","fen":"rn5k/1pn1r2Q/p1qpbNp1/4p3/4P1P1/5P2/PPP1N3/2KR1B1R b - - 0 20","moves":"e7h7 h1h7","rating":1162,"ratingDeviation":86,"randomNumberQuery":4277,"popularity":85,"nbPlays":209,"themes":["arabianMate","kingsideAttack","mate","mateIn1","middlegame","oneMove"],"gameUrl":"https://lichess.org/IsexVoLn/black#39","openingFamily":"","openingVariation":"","__v":0},{"theme":"","_id":"65e8c983a5e6cd0e9be2f709","uid":"u7I2N","fen":"2b2Q1k/r3q2p/4pNp1/3pP3/pp6/7R/PPP2PP1/2K4R b - - 0 26","moves":"e7f8 h3h7 a7h7 h1h7","rating":1161,"ratingDeviation":82,"randomNumberQuery":9297,"popularity":81,"nbPlays":149,"themes":["arabianMate","endgame","kingsideAttack","master","masterVsMaster","mate","mateIn2","short"],"gameUrl":"https://lichess.org/NKpPBZKW/black#51","openingFamily":"","openingVariation":"","__v":0},{"theme":"","_id":"65e8c9d9a5e6cd0e9be410ff","uid":"uiN6O","fen":"6rk/5p2/8/p3pBq1/2N1P2p/1P3n1Q/P4P2/R6K w - - 2 35","moves":"c4d6 g5g1 a1g1 g8g1","rating":1166,"ratingDeviation":81,"randomNumberQuery":5900,"popularity":45,"nbPlays":201,"themes":["arabianMate","mate","mateIn2","middlegame","sacrifice","short"],"gameUrl":"https://lichess.org/gFjKGeFI#68","openingFamily":"","openingVariation":"","__v":0},{"theme":"","_id":"65e8c9dfa5e6cd0e9be4228b","uid":"ukbkv","fen":"7k/R7/5N2/4p2b/P7/2P1P3/1r5r/6K1 b - - 0 34","moves":"h2c2 a7h7","rating":1178,"ratingDeviation":80,"randomNumberQuery":6206,"popularity":78,"nbPlays":290,"themes":["arabianMate","endgame","mate","mateIn1","oneMove"],"gameUrl":"https://lichess.org/gikYIAjT/black#67","openingFamily":"","openingVariation":"","__v":0},{"theme":"","_id":"65e8c9e4a5e6cd0e9be4358f","uid":"un6m7","fen":"1k6/pp4p1/1Bn2p1p/4pQ2/2P1N3/1P6/P5PP/3rn2K w - - 1 27","moves":"f5h5 e1f3 b6g1 d1g1","rating":1169,"ratingDeviation":80,"randomNumberQuery":1793,"popularity":89,"nbPlays":1090,"themes":["arabianMate","discoveredAttack","endgame","mate","mateIn2","short"],"gameUrl":"https://lichess.org/SVTShwD4#52","openingFamily":"","openingVariation":"","__v":0},{"theme":"","_id":"65e8cb17a5e6cd0e9be8532f","uid":"x1Fx4","fen":"2R5/p1p3pp/1p4kr/3P2n1/P5r1/B1P1P3/5PPP/5RK1 w - - 7 26","moves":"c8c7 g5f3 g1h1 h6h2","rating":1169,"ratingDeviation":77,"randomNumberQuery":645,"popularity":89,"nbPlays":678,"themes":["arabianMate","endgame","mate","mateIn2","pin","short"],"gameUrl":"https://lichess.org/yWSr6ch6#50","openingFamily":"","openingVariation":"","__v":0},{"theme":"","_id":"65e8cb56a5e6cd0e9be93351","uid":"xUJ7d","fen":"k2b2r1/rp1q2p1/R1Np3p/2pPp1p1/4P3/1RP5/1P2QPPP/6K1 b - - 0 29","moves":"a7a6 e2a6 b7a6 b3b8","rating":1177,"ratingDeviation":76,"randomNumberQuery":3502,"popularity":96,"nbPlays":15259,"themes":["arabianMate","mate","mateIn2","middlegame","queensideAttack","sacrifice","short"],"gameUrl":"https://lichess.org/rk6RXNbl/black#57","openingFamily":"","openingVariation":"","__v":0},{"theme":"","_id":"65e8cb61a5e6cd0e9be959e7","uid":"xZP7p","fen":"r2q1r1k/pp2npbp/2p2NP1/4n1B1/3p2P1/2PB1Q2/PP3P2/R3K2R b KQ - 0 16","moves":"f7g6 h1h7","rating":1179,"ratingDeviation":80,"randomNumberQuery":6719,"popularity":93,"nbPlays":160,"themes":["arabianMate","kingsideAttack","mate","mateIn1","middlegame","oneMove"],"gameUrl":"https://lichess.org/fcyvP2vt/black#31","openingFamily":"Modern_Defense","openingVariation":"Modern_Defense_Other_variations","__v":0},{"theme":"","_id":"65e8cb6fa5e6cd0e9be98982","uid":"xfjyO","fen":"r1b2r1k/ppq2pbp/2n1pNp1/2p1n1B1/5P1N/3P3R/PPP3PP/R2Q2K1 b - - 0 17","moves":"e5d7 h4g6 f7g6 h3h7","rating":1178,"ratingDeviation":76,"randomNumberQuery":6942,"popularity":93,"nbPlays":5192,"themes":["arabianMate","discoveredAttack","kingsideAttack","mate","mateIn2","middlegame","pin","short"],"gameUrl":"https://lichess.org/eCH5lPXr/black#33","openingFamily":"Sicilian_Defense","openingVariation":"Sicilian_Defense_Hyperaccelerated_Dragon","__v":0},{"theme":"","_id":"65e8cbfaa5e6cd0e9beb642a","uid":"yfohg","fen":"4r2k/p2R2R1/1pp2N2/8/8/2K2P2/bPP4r/8 b - - 1 29","moves":"e8f8 g7h7 h2h7 d7h7","rating":1172,"ratingDeviation":82,"randomNumberQuery":2112,"popularity":83,"nbPlays":603,"themes":["arabianMate","endgame","mate","mateIn2","short"],"gameUrl":"https://lichess.org/CbOe8qXF/black#57","openingFamily":"","openingVariation":"","__v":0},{"theme":"","_id":"65e8cc3fa5e6cd0e9bec4f02","uid":"zAOoJ","fen":"r1b2rk1/pp3q1n/3p1N2/6pQ/4P3/3PP3/P2K4/7R b - - 0 20","moves":"g8h8 h5h7 f7h7 h1h7","rating":1176,"ratingDeviation":83,"randomNumberQuery":5676,"popularity":81,"nbPlays":278,"themes":["arabianMate","mate","mateIn2","middlegame","short"],"gameUrl":"https://lichess.org/e17OFMCB/black#39","openingFamily":"","openingVariation":"","__v":0},{"theme":"","_id":"65e8cc4fa5e6cd0e9bec8808","uid":"zHoMk","fen":"4r1k1/2R4p/b3p3/p2p2p1/3N1pN1/8/1n3PPP/6K1 b - - 1 27","moves":"e8c8 g4f6 g8h8 c7h7","rating":1170,"ratingDeviation":74,"randomNumberQuery":8657,"popularity":94,"nbPlays":5904,"themes":["arabianMate","endgame","mate","mateIn2","short"],"gameUrl":"https://lichess.org/CeSaUgfw/black#53","openingFamily":"","openingVariation":"","__v":0},{"theme":"","_id":"65e8cc89a5e6cd0e9bed5514","uid":"zinKc","fen":"8/3p2k1/6R1/q2NpP2/2PbP3/1P1K4/r7/8 b - - 2 46","moves":"g7h7 d5f6 h7h8 g6g8","rating":1160,"ratingDeviation":77,"randomNumberQuery":2329,"popularity":92,"nbPlays":1089,"themes":["arabianMate","endgame","mate","mateIn2","short"],"gameUrl":"https://lichess.org/09IMPhaJ/black#91","openingFamily":"","openingVariation":"","__v":0}]